{
    "深入挖掘历史文化资源": [
        {
            "time": "2025-01-20 00:13:12.265215+08:00",
            "hot_index": "7929321"
        },
        {
            "time": "2025-01-20 00:33:00.165838+08:00",
            "hot_index": "7931948"
        },
        {
            "time": "2025-01-20 00:43:35.569021+08:00",
            "hot_index": "7995399"
        },
        {
            "time": "2025-01-20 01:10:01.473454+08:00",
            "hot_index": "7982231"
        },
        {
            "time": "2025-01-20 01:28:30.912134+08:00",
            "hot_index": "7959302"
        },
        {
            "time": "2025-01-20 01:43:50.192560+08:00",
            "hot_index": "7996700"
        },
        {
            "time": "2025-01-20 02:14:41.430893+08:00",
            "hot_index": "7921861"
        },
        {
            "time": "2025-01-20 02:33:24.127994+08:00",
            "hot_index": "7908440"
        },
        {
            "time": "2025-01-20 02:45:14.081563+08:00",
            "hot_index": "7964434"
        },
        {
            "time": "2025-01-20 03:09:06.022243+08:00",
            "hot_index": "7977097"
        },
        {
            "time": "2025-01-20 03:23:39.746335+08:00",
            "hot_index": "7974750"
        },
        {
            "time": "2025-01-20 03:43:35.673651+08:00",
            "hot_index": "7910388"
        },
        {
            "time": "2025-01-20 04:11:58.732404+08:00",
            "hot_index": "7933357"
        },
        {
            "time": "2025-01-20 04:27:56.486948+08:00",
            "hot_index": "7906800"
        },
        {
            "time": "2025-01-20 04:43:55.614944+08:00",
            "hot_index": "7981062"
        }
    ],
    "多人感染甲流后出现面瘫": [
        {
            "time": "2025-01-20 00:13:12.265215+08:00",
            "hot_index": "7942961"
        },
        {
            "time": "2025-01-20 00:33:00.165838+08:00",
            "hot_index": "7916422"
        },
        {
            "time": "2025-01-20 00:43:35.569021+08:00",
            "hot_index": "7983507"
        },
        {
            "time": "2025-01-20 01:10:01.473454+08:00",
            "hot_index": "7969901"
        },
        {
            "time": "2025-01-20 01:28:30.912134+08:00",
            "hot_index": "7949654"
        },
        {
            "time": "2025-01-20 01:43:50.192560+08:00",
            "hot_index": "7925123"
        },
        {
            "time": "2025-01-20 02:14:41.430893+08:00",
            "hot_index": "7958963"
        },
        {
            "time": "2025-01-20 02:33:24.127994+08:00",
            "hot_index": "7931934"
        },
        {
            "time": "2025-01-20 02:45:14.081563+08:00",
            "hot_index": "7999462"
        },
        {
            "time": "2025-01-20 03:09:06.022243+08:00",
            "hot_index": "7909427"
        },
        {
            "time": "2025-01-20 03:23:39.746335+08:00",
            "hot_index": "7985904"
        },
        {
            "time": "2025-01-20 03:43:35.673651+08:00",
            "hot_index": "7970060"
        },
        {
            "time": "2025-01-20 04:11:58.732404+08:00",
            "hot_index": "7981728"
        },
        {
            "time": "2025-01-20 04:27:56.486948+08:00",
            "hot_index": "7934738"
        },
        {
            "time": "2025-01-20 04:43:55.614944+08:00",
            "hot_index": "7962345"
        }
    ],
    "《漂白》尺度绝了": [
        {
            "time": "2025-01-20 00:13:12.265215+08:00",
            "hot_index": "7875075"
        },
        {
            "time": "2025-01-20 00:33:00.165838+08:00",
            "hot_index": "7858143"
        },
        {
            "time": "2025-01-20 00:43:35.569021+08:00",
            "hot_index": "7836090"
        },
        {
            "time": "2025-01-20 01:10:01.473454+08:00",
            "hot_index": "7870793"
        },
        {
            "time": "2025-01-20 01:28:30.912134+08:00",
            "hot_index": "7842781"
        },
        {
            "time": "2025-01-20 01:43:50.192560+08:00",
            "hot_index": "7846198"
        },
        {
            "time": "2025-01-20 02:14:41.430893+08:00",
            "hot_index": "7878798"
        },
        {
            "time": "2025-01-20 02:33:24.127994+08:00",
            "hot_index": "7856935"
        },
        {
            "time": "2025-01-20 02:45:14.081563+08:00",
            "hot_index": "7895311"
        },
        {
            "time": "2025-01-20 03:09:06.022243+08:00",
            "hot_index": "7806727"
        },
        {
            "time": "2025-01-20 03:23:39.746335+08:00",
            "hot_index": "7827723"
        },
        {
            "time": "2025-01-20 03:43:35.673651+08:00",
            "hot_index": "7815294"
        },
        {
            "time": "2025-01-20 04:11:58.732404+08:00",
            "hot_index": "7896109"
        },
        {
            "time": "2025-01-20 04:27:56.486948+08:00",
            "hot_index": "7877667"
        },
        {
            "time": "2025-01-20 04:43:55.614944+08:00",
            "hot_index": "7835639"
        }
    ],
    "从工业设计感受制造强国的蓬勃脉动": [
        {
            "time": "2025-01-20 00:13:12.265215+08:00",
            "hot_index": "7705215"
        },
        {
            "time": "2025-01-20 00:33:00.165838+08:00",
            "hot_index": "7742884"
        },
        {
            "time": "2025-01-20 00:43:35.569021+08:00",
            "hot_index": "7762079"
        },
        {
            "time": "2025-01-20 01:10:01.473454+08:00",
            "hot_index": "7773537"
        },
        {
            "time": "2025-01-20 01:28:30.912134+08:00",
            "hot_index": "7791542"
        },
        {
            "time": "2025-01-20 01:43:50.192560+08:00",
            "hot_index": "7727073"
        },
        {
            "time": "2025-01-20 02:14:41.430893+08:00",
            "hot_index": "7717005"
        },
        {
            "time": "2025-01-20 02:33:24.127994+08:00",
            "hot_index": "7734594"
        },
        {
            "time": "2025-01-20 02:45:14.081563+08:00",
            "hot_index": "7749553"
        },
        {
            "time": "2025-01-20 03:09:06.022243+08:00",
            "hot_index": "7749099"
        },
        {
            "time": "2025-01-20 03:23:39.746335+08:00",
            "hot_index": "7747761"
        },
        {
            "time": "2025-01-20 03:43:35.673651+08:00",
            "hot_index": "7706910"
        },
        {
            "time": "2025-01-20 04:11:58.732404+08:00",
            "hot_index": "7737860"
        },
        {
            "time": "2025-01-20 04:27:56.486948+08:00",
            "hot_index": "7785861"
        },
        {
            "time": "2025-01-20 04:43:55.614944+08:00",
            "hot_index": "7788086"
        }
    ],
    "央视曝光美甲背后隐患": [
        {
            "time": "2025-01-20 00:13:12.265215+08:00",
            "hot_index": "7617878"
        },
        {
            "time": "2025-01-20 00:33:00.165838+08:00",
            "hot_index": "7614356"
        },
        {
            "time": "2025-01-20 00:43:35.569021+08:00",
            "hot_index": "7621070"
        },
        {
            "time": "2025-01-20 01:10:01.473454+08:00",
            "hot_index": "7644972"
        },
        {
            "time": "2025-01-20 01:28:30.912134+08:00",
            "hot_index": "7636463"
        },
        {
            "time": "2025-01-20 01:43:50.192560+08:00",
            "hot_index": "7653176"
        },
        {
            "time": "2025-01-20 02:14:41.430893+08:00",
            "hot_index": "7619270"
        },
        {
            "time": "2025-01-20 02:33:24.127994+08:00",
            "hot_index": "7688476"
        },
        {
            "time": "2025-01-20 02:45:14.081563+08:00",
            "hot_index": "7659462"
        },
        {
            "time": "2025-01-20 03:09:06.022243+08:00",
            "hot_index": "7689367"
        },
        {
            "time": "2025-01-20 03:23:39.746335+08:00",
            "hot_index": "7615618"
        },
        {
            "time": "2025-01-20 03:43:35.673651+08:00",
            "hot_index": "7622897"
        },
        {
            "time": "2025-01-20 04:11:58.732404+08:00",
            "hot_index": "7654894"
        },
        {
            "time": "2025-01-20 04:27:56.486948+08:00",
            "hot_index": "7691867"
        },
        {
            "time": "2025-01-20 04:43:55.614944+08:00",
            "hot_index": "7676078"
        }
    ],
    "官宣！央视春晚主持人确定": [
        {
            "time": "2025-01-20 00:13:12.265215+08:00",
            "hot_index": "7558016"
        },
        {
            "time": "2025-01-20 00:33:00.165838+08:00",
            "hot_index": "7580843"
        },
        {
            "time": "2025-01-20 00:43:35.569021+08:00",
            "hot_index": "7569291"
        },
        {
            "time": "2025-01-20 01:10:01.473454+08:00",
            "hot_index": "7528248"
        },
        {
            "time": "2025-01-20 01:28:30.912134+08:00",
            "hot_index": "7501455"
        },
        {
            "time": "2025-01-20 01:43:50.192560+08:00",
            "hot_index": "7528121"
        },
        {
            "time": "2025-01-20 02:14:41.430893+08:00",
            "hot_index": "7590333"
        },
        {
            "time": "2025-01-20 02:33:24.127994+08:00",
            "hot_index": "7552657"
        },
        {
            "time": "2025-01-20 02:45:14.081563+08:00",
            "hot_index": "7502582"
        },
        {
            "time": "2025-01-20 03:09:06.022243+08:00",
            "hot_index": "7596822"
        },
        {
            "time": "2025-01-20 03:23:39.746335+08:00",
            "hot_index": "7512323"
        },
        {
            "time": "2025-01-20 03:43:35.673651+08:00",
            "hot_index": "7584864"
        },
        {
            "time": "2025-01-20 04:11:58.732404+08:00",
            "hot_index": "7582516"
        },
        {
            "time": "2025-01-20 04:27:56.486948+08:00",
            "hot_index": "7539081"
        },
        {
            "time": "2025-01-20 04:43:55.614944+08:00",
            "hot_index": "7506549"
        }
    ],
    "尹锡悦正式进入拘留所": [
        {
            "time": "2025-01-20 00:13:12.265215+08:00",
            "hot_index": "7414032"
        },
        {
            "time": "2025-01-20 00:33:00.165838+08:00",
            "hot_index": "7470215"
        },
        {
            "time": "2025-01-20 00:43:35.569021+08:00",
            "hot_index": "7480014"
        },
        {
            "time": "2025-01-20 01:10:01.473454+08:00",
            "hot_index": "7406611"
        },
        {
            "time": "2025-01-20 01:28:30.912134+08:00",
            "hot_index": "7470091"
        },
        {
            "time": "2025-01-20 01:43:50.192560+08:00",
            "hot_index": "7438558"
        },
        {
            "time": "2025-01-20 02:14:41.430893+08:00",
            "hot_index": "7412704"
        },
        {
            "time": "2025-01-20 02:33:24.127994+08:00",
            "hot_index": "7490635"
        },
        {
            "time": "2025-01-20 02:45:14.081563+08:00",
            "hot_index": "7406024"
        },
        {
            "time": "2025-01-20 03:09:06.022243+08:00",
            "hot_index": "7494771"
        },
        {
            "time": "2025-01-20 03:23:39.746335+08:00",
            "hot_index": "7427109"
        },
        {
            "time": "2025-01-20 03:43:35.673651+08:00",
            "hot_index": "7446242"
        },
        {
            "time": "2025-01-20 04:11:58.732404+08:00",
            "hot_index": "7420740"
        },
        {
            "time": "2025-01-20 04:27:56.486948+08:00",
            "hot_index": "7440960"
        },
        {
            "time": "2025-01-20 04:43:55.614944+08:00",
            "hot_index": "7419043"
        }
    ],
    "9岁小男孩娴熟解剖动物内脏": [
        {
            "time": "2025-01-20 00:13:12.265215+08:00",
            "hot_index": "7357078"
        },
        {
            "time": "2025-01-20 00:33:00.165838+08:00",
            "hot_index": "7310814"
        },
        {
            "time": "2025-01-20 00:43:35.569021+08:00",
            "hot_index": "7360844"
        },
        {
            "time": "2025-01-20 01:10:01.473454+08:00",
            "hot_index": "7378616"
        },
        {
            "time": "2025-01-20 01:28:30.912134+08:00",
            "hot_index": "7345506"
        },
        {
            "time": "2025-01-20 01:43:50.192560+08:00",
            "hot_index": "7337724"
        },
        {
            "time": "2025-01-20 02:14:41.430893+08:00",
            "hot_index": "7325153"
        },
        {
            "time": "2025-01-20 02:33:24.127994+08:00",
            "hot_index": "7363609"
        },
        {
            "time": "2025-01-20 02:45:14.081563+08:00",
            "hot_index": "7341502"
        },
        {
            "time": "2025-01-20 03:09:06.022243+08:00",
            "hot_index": "7346423"
        },
        {
            "time": "2025-01-20 03:23:39.746335+08:00",
            "hot_index": "7314729"
        },
        {
            "time": "2025-01-20 03:43:35.673651+08:00",
            "hot_index": "7327451"
        },
        {
            "time": "2025-01-20 04:11:58.732404+08:00",
            "hot_index": "7326004"
        },
        {
            "time": "2025-01-20 04:27:56.486948+08:00",
            "hot_index": "7312243"
        },
        {
            "time": "2025-01-20 04:43:55.614944+08:00",
            "hot_index": "7383442"
        }
    ],
    "特朗普发帖呼吁挽救TikTok": [
        {
            "time": "2025-01-20 00:13:12.265215+08:00",
            "hot_index": "7265033"
        },
        {
            "time": "2025-01-20 00:33:00.165838+08:00",
            "hot_index": "7258189"
        },
        {
            "time": "2025-01-20 00:43:35.569021+08:00",
            "hot_index": "6988211"
        },
        {
            "time": "2025-01-20 01:10:01.473454+08:00",
            "hot_index": "6941157"
        },
        {
            "time": "2025-01-20 01:28:30.912134+08:00",
            "hot_index": "6972536"
        },
        {
            "time": "2025-01-20 01:43:50.192560+08:00",
            "hot_index": "6931524"
        },
        {
            "time": "2025-01-20 02:14:41.430893+08:00",
            "hot_index": "6922668"
        },
        {
            "time": "2025-01-20 02:33:24.127994+08:00",
            "hot_index": "6971018"
        },
        {
            "time": "2025-01-20 02:45:14.081563+08:00",
            "hot_index": "6971769"
        },
        {
            "time": "2025-01-20 03:09:06.022243+08:00",
            "hot_index": "6962151"
        },
        {
            "time": "2025-01-20 03:23:39.746335+08:00",
            "hot_index": "6914456"
        },
        {
            "time": "2025-01-20 03:43:35.673651+08:00",
            "hot_index": "6927073"
        },
        {
            "time": "2025-01-20 04:11:58.732404+08:00",
            "hot_index": "6948193"
        },
        {
            "time": "2025-01-20 04:27:56.486948+08:00",
            "hot_index": "6927465"
        },
        {
            "time": "2025-01-20 04:43:55.614944+08:00",
            "hot_index": "6973278"
        }
    ],
    "一路繁花窒息七分钟": [
        {
            "time": "2025-01-20 00:13:12.265215+08:00",
            "hot_index": "7164357"
        },
        {
            "time": "2025-01-20 00:33:00.165838+08:00",
            "hot_index": "7135719"
        },
        {
            "time": "2025-01-20 00:43:35.569021+08:00",
            "hot_index": "7140284"
        },
        {
            "time": "2025-01-20 01:10:01.473454+08:00",
            "hot_index": "7137674"
        },
        {
            "time": "2025-01-20 01:28:30.912134+08:00",
            "hot_index": "7179216"
        },
        {
            "time": "2025-01-20 01:43:50.192560+08:00",
            "hot_index": "7170495"
        },
        {
            "time": "2025-01-20 02:14:41.430893+08:00",
            "hot_index": "7167625"
        },
        {
            "time": "2025-01-20 02:33:24.127994+08:00",
            "hot_index": "7194117"
        },
        {
            "time": "2025-01-20 02:45:14.081563+08:00",
            "hot_index": "7197369"
        },
        {
            "time": "2025-01-20 03:09:06.022243+08:00",
            "hot_index": "7111594"
        },
        {
            "time": "2025-01-20 03:23:39.746335+08:00",
            "hot_index": "7186276"
        },
        {
            "time": "2025-01-20 03:43:35.673651+08:00",
            "hot_index": "7184534"
        },
        {
            "time": "2025-01-20 04:11:58.732404+08:00",
            "hot_index": "7154105"
        },
        {
            "time": "2025-01-20 04:27:56.486948+08:00",
            "hot_index": "7103210"
        },
        {
            "time": "2025-01-20 04:43:55.614944+08:00",
            "hot_index": "7104564"
        }
    ],
    "建议趁周末补个觉": [
        {
            "time": "2025-01-20 00:13:12.265215+08:00",
            "hot_index": "7068235"
        },
        {
            "time": "2025-01-20 00:33:00.165838+08:00",
            "hot_index": "7013760"
        },
        {
            "time": "2025-01-20 00:43:35.569021+08:00",
            "hot_index": "7042147"
        },
        {
            "time": "2025-01-20 01:10:01.473454+08:00",
            "hot_index": "7022284"
        },
        {
            "time": "2025-01-20 01:28:30.912134+08:00",
            "hot_index": "7009087"
        },
        {
            "time": "2025-01-20 01:43:50.192560+08:00",
            "hot_index": "7099418"
        },
        {
            "time": "2025-01-20 02:14:41.430893+08:00",
            "hot_index": "7036645"
        },
        {
            "time": "2025-01-20 02:33:24.127994+08:00",
            "hot_index": "7051780"
        },
        {
            "time": "2025-01-20 02:45:14.081563+08:00",
            "hot_index": "7075831"
        },
        {
            "time": "2025-01-20 03:09:06.022243+08:00",
            "hot_index": "7018613"
        },
        {
            "time": "2025-01-20 03:23:39.746335+08:00",
            "hot_index": "7029042"
        },
        {
            "time": "2025-01-20 03:43:35.673651+08:00",
            "hot_index": "7016401"
        },
        {
            "time": "2025-01-20 04:11:58.732404+08:00",
            "hot_index": "7075114"
        },
        {
            "time": "2025-01-20 04:27:56.486948+08:00",
            "hot_index": "7007342"
        },
        {
            "time": "2025-01-20 04:43:55.614944+08:00",
            "hot_index": "7075042"
        }
    ],
    "放弃鸡娃的中产 捧红这个小众工作": [
        {
            "time": "2025-01-20 00:13:12.265215+08:00",
            "hot_index": "6907158"
        },
        {
            "time": "2025-01-20 00:33:00.165838+08:00",
            "hot_index": "6988275"
        },
        {
            "time": "2025-01-20 01:43:50.192560+08:00",
            "hot_index": "3586571"
        },
        {
            "time": "2025-01-20 02:14:41.430893+08:00",
            "hot_index": "6060067"
        },
        {
            "time": "2025-01-20 02:33:24.127994+08:00",
            "hot_index": "6308974"
        },
        {
            "time": "2025-01-20 02:45:14.081563+08:00",
            "hot_index": "6794349"
        },
        {
            "time": "2025-01-20 03:09:06.022243+08:00",
            "hot_index": "5822242"
        },
        {
            "time": "2025-01-20 03:23:39.746335+08:00",
            "hot_index": "5321897"
        },
        {
            "time": "2025-01-20 03:43:35.673651+08:00",
            "hot_index": "4466668"
        },
        {
            "time": "2025-01-20 04:11:58.732404+08:00",
            "hot_index": "6746701"
        },
        {
            "time": "2025-01-20 04:27:56.486948+08:00",
            "hot_index": "6598153"
        },
        {
            "time": "2025-01-20 04:43:55.614944+08:00",
            "hot_index": "4564123"
        }
    ],
    "浙江村民装光伏被骗百万？假的": [
        {
            "time": "2025-01-20 00:13:12.265215+08:00",
            "hot_index": "6895250"
        },
        {
            "time": "2025-01-20 00:33:00.165838+08:00",
            "hot_index": "6831342"
        },
        {
            "time": "2025-01-20 00:43:35.569021+08:00",
            "hot_index": "6871158"
        },
        {
            "time": "2025-01-20 01:10:01.473454+08:00",
            "hot_index": "6815389"
        },
        {
            "time": "2025-01-20 01:28:30.912134+08:00",
            "hot_index": "6862411"
        },
        {
            "time": "2025-01-20 01:43:50.192560+08:00",
            "hot_index": "6892993"
        },
        {
            "time": "2025-01-20 02:14:41.430893+08:00",
            "hot_index": "6895225"
        },
        {
            "time": "2025-01-20 02:33:24.127994+08:00",
            "hot_index": "6818269"
        },
        {
            "time": "2025-01-20 02:45:14.081563+08:00",
            "hot_index": "6804105"
        },
        {
            "time": "2025-01-20 03:09:06.022243+08:00",
            "hot_index": "6814559"
        },
        {
            "time": "2025-01-20 03:23:39.746335+08:00",
            "hot_index": "6843526"
        },
        {
            "time": "2025-01-20 03:43:35.673651+08:00",
            "hot_index": "6830453"
        },
        {
            "time": "2025-01-20 04:11:58.732404+08:00",
            "hot_index": "6828669"
        },
        {
            "time": "2025-01-20 04:27:56.486948+08:00",
            "hot_index": "6871842"
        },
        {
            "time": "2025-01-20 04:43:55.614944+08:00",
            "hot_index": "6836223"
        }
    ],
    "白鹿残梅映血": [
        {
            "time": "2025-01-20 00:13:12.265215+08:00",
            "hot_index": "6746635"
        }
    ],
    "中国年轻人捡漏日本低价中古屋": [
        {
            "time": "2025-01-20 00:13:12.265215+08:00",
            "hot_index": "6635714"
        },
        {
            "time": "2025-01-20 02:14:41.430893+08:00",
            "hot_index": "3100000"
        },
        {
            "time": "2025-01-20 03:09:06.022243+08:00",
            "hot_index": "3231037"
        },
        {
            "time": "2025-01-20 03:23:39.746335+08:00",
            "hot_index": "6436155"
        },
        {
            "time": "2025-01-20 04:27:56.486948+08:00",
            "hot_index": "3183602"
        }
    ],
    "电商平台被指骗取国补": [
        {
            "time": "2025-01-20 00:13:12.265215+08:00",
            "hot_index": "6592974"
        },
        {
            "time": "2025-01-20 00:33:00.165838+08:00",
            "hot_index": "6498533"
        },
        {
            "time": "2025-01-20 00:43:35.569021+08:00",
            "hot_index": "6554213"
        },
        {
            "time": "2025-01-20 01:10:01.473454+08:00",
            "hot_index": "5539770"
        },
        {
            "time": "2025-01-20 01:28:30.912134+08:00",
            "hot_index": "6032439"
        },
        {
            "time": "2025-01-20 01:43:50.192560+08:00",
            "hot_index": "5751783"
        },
        {
            "time": "2025-01-20 02:14:41.430893+08:00",
            "hot_index": "5007225"
        },
        {
            "time": "2025-01-20 02:33:24.127994+08:00",
            "hot_index": "4412616"
        },
        {
            "time": "2025-01-20 02:45:14.081563+08:00",
            "hot_index": "3522121"
        },
        {
            "time": "2025-01-20 03:09:06.022243+08:00",
            "hot_index": "6423055"
        },
        {
            "time": "2025-01-20 03:23:39.746335+08:00",
            "hot_index": "6151742"
        },
        {
            "time": "2025-01-20 03:43:35.673651+08:00",
            "hot_index": "3100000"
        },
        {
            "time": "2025-01-20 04:11:58.732404+08:00",
            "hot_index": "3431859"
        },
        {
            "time": "2025-01-20 04:27:56.486948+08:00",
            "hot_index": "3100000"
        },
        {
            "time": "2025-01-20 04:43:55.614944+08:00",
            "hot_index": "3608323"
        }
    ],
    "3岁宝宝全身起皮脱衣服像下雪": [
        {
            "time": "2025-01-20 00:13:12.265215+08:00",
            "hot_index": "6480721"
        },
        {
            "time": "2025-01-20 00:33:00.165838+08:00",
            "hot_index": "6009704"
        },
        {
            "time": "2025-01-20 00:43:35.569021+08:00",
            "hot_index": "5319103"
        },
        {
            "time": "2025-01-20 01:10:01.473454+08:00",
            "hot_index": "4919279"
        },
        {
            "time": "2025-01-20 01:28:30.912134+08:00",
            "hot_index": "5696745"
        },
        {
            "time": "2025-01-20 01:43:50.192560+08:00",
            "hot_index": "5058337"
        },
        {
            "time": "2025-01-20 02:14:41.430893+08:00",
            "hot_index": "5114360"
        },
        {
            "time": "2025-01-20 02:33:24.127994+08:00",
            "hot_index": "4563537"
        },
        {
            "time": "2025-01-20 02:45:14.081563+08:00",
            "hot_index": "4588951"
        },
        {
            "time": "2025-01-20 03:09:06.022243+08:00",
            "hot_index": "4902592"
        },
        {
            "time": "2025-01-20 03:23:39.746335+08:00",
            "hot_index": "5415841"
        },
        {
            "time": "2025-01-20 03:43:35.673651+08:00",
            "hot_index": "4597705"
        },
        {
            "time": "2025-01-20 04:11:58.732404+08:00",
            "hot_index": "4381500"
        },
        {
            "time": "2025-01-20 04:27:56.486948+08:00",
            "hot_index": "3839603"
        },
        {
            "time": "2025-01-20 04:43:55.614944+08:00",
            "hot_index": "4684852"
        }
    ],
    "留几手曝杨子留了90%的现金给黄圣依": [
        {
            "time": "2025-01-20 00:13:12.265215+08:00",
            "hot_index": "6369728"
        },
        {
            "time": "2025-01-20 02:33:24.127994+08:00",
            "hot_index": "5941135"
        },
        {
            "time": "2025-01-20 03:43:35.673651+08:00",
            "hot_index": "5781066"
        }
    ],
    "男子约前妻男友饮酒后死亡": [
        {
            "time": "2025-01-20 00:13:12.265215+08:00",
            "hot_index": "6224184"
        },
        {
            "time": "2025-01-20 00:33:00.165838+08:00",
            "hot_index": "4622901"
        },
        {
            "time": "2025-01-20 01:10:01.473454+08:00",
            "hot_index": "5413619"
        },
        {
            "time": "2025-01-20 01:28:30.912134+08:00",
            "hot_index": "5017090"
        },
        {
            "time": "2025-01-20 01:43:50.192560+08:00",
            "hot_index": "6524010"
        },
        {
            "time": "2025-01-20 02:14:41.430893+08:00",
            "hot_index": "6459350"
        },
        {
            "time": "2025-01-20 02:33:24.127994+08:00",
            "hot_index": "6528220"
        },
        {
            "time": "2025-01-20 02:45:14.081563+08:00",
            "hot_index": "5218773"
        },
        {
            "time": "2025-01-20 03:09:06.022243+08:00",
            "hot_index": "6371410"
        },
        {
            "time": "2025-01-20 03:23:39.746335+08:00",
            "hot_index": "6314397"
        },
        {
            "time": "2025-01-20 03:43:35.673651+08:00",
            "hot_index": "6114839"
        },
        {
            "time": "2025-01-20 04:11:58.732404+08:00",
            "hot_index": "6417213"
        },
        {
            "time": "2025-01-20 04:27:56.486948+08:00",
            "hot_index": "6739325"
        },
        {
            "time": "2025-01-20 04:43:55.614944+08:00",
            "hot_index": "6114313"
        }
    ],
    "这届年轻人开始“整顿”年味了": [
        {
            "time": "2025-01-20 00:13:12.265215+08:00",
            "hot_index": "6174775"
        },
        {
            "time": "2025-01-20 00:33:00.165838+08:00",
            "hot_index": "4456184"
        },
        {
            "time": "2025-01-20 00:43:35.569021+08:00",
            "hot_index": "3646759"
        },
        {
            "time": "2025-01-20 01:10:01.473454+08:00",
            "hot_index": "6099942"
        },
        {
            "time": "2025-01-20 01:28:30.912134+08:00",
            "hot_index": "6223332"
        },
        {
            "time": "2025-01-20 01:43:50.192560+08:00",
            "hot_index": "6265934"
        },
        {
            "time": "2025-01-20 02:14:41.430893+08:00",
            "hot_index": "5884409"
        },
        {
            "time": "2025-01-20 02:33:24.127994+08:00",
            "hot_index": "6489015"
        },
        {
            "time": "2025-01-20 02:45:14.081563+08:00",
            "hot_index": "6324672"
        },
        {
            "time": "2025-01-20 03:09:06.022243+08:00",
            "hot_index": "4344733"
        },
        {
            "time": "2025-01-20 03:23:39.746335+08:00",
            "hot_index": "3708207"
        },
        {
            "time": "2025-01-20 04:11:58.732404+08:00",
            "hot_index": "5278109"
        },
        {
            "time": "2025-01-20 04:27:56.486948+08:00",
            "hot_index": "6421651"
        },
        {
            "time": "2025-01-20 04:43:55.614944+08:00",
            "hot_index": "6662426"
        }
    ],
    "初中生用70元自制望远镜可观测月球": [
        {
            "time": "2025-01-20 00:13:12.265215+08:00",
            "hot_index": "6056656"
        },
        {
            "time": "2025-01-20 00:33:00.165838+08:00",
            "hot_index": "5760778"
        },
        {
            "time": "2025-01-20 00:43:35.569021+08:00",
            "hot_index": "6466950"
        },
        {
            "time": "2025-01-20 01:10:01.473454+08:00",
            "hot_index": "3641815"
        },
        {
            "time": "2025-01-20 01:28:30.912134+08:00",
            "hot_index": "3937969"
        },
        {
            "time": "2025-01-20 01:43:50.192560+08:00",
            "hot_index": "4263457"
        },
        {
            "time": "2025-01-20 02:14:41.430893+08:00",
            "hot_index": "5296369"
        },
        {
            "time": "2025-01-20 02:33:24.127994+08:00",
            "hot_index": "4386248"
        },
        {
            "time": "2025-01-20 02:45:14.081563+08:00",
            "hot_index": "5497669"
        },
        {
            "time": "2025-01-20 03:09:06.022243+08:00",
            "hot_index": "5048509"
        },
        {
            "time": "2025-01-20 03:23:39.746335+08:00",
            "hot_index": "4957785"
        },
        {
            "time": "2025-01-20 03:43:35.673651+08:00",
            "hot_index": "3947939"
        },
        {
            "time": "2025-01-20 04:11:58.732404+08:00",
            "hot_index": "4622798"
        },
        {
            "time": "2025-01-20 04:27:56.486948+08:00",
            "hot_index": "5200346"
        },
        {
            "time": "2025-01-20 04:43:55.614944+08:00",
            "hot_index": "4897868"
        }
    ],
    "谢金燕承认未婚生子": [
        {
            "time": "2025-01-20 00:13:12.265215+08:00",
            "hot_index": "5919935"
        },
        {
            "time": "2025-01-20 00:33:00.165838+08:00",
            "hot_index": "5956229"
        },
        {
            "time": "2025-01-20 00:43:35.569021+08:00",
            "hot_index": "5900897"
        },
        {
            "time": "2025-01-20 01:10:01.473454+08:00",
            "hot_index": "5078163"
        },
        {
            "time": "2025-01-20 01:28:30.912134+08:00",
            "hot_index": "5392335"
        },
        {
            "time": "2025-01-20 01:43:50.192560+08:00",
            "hot_index": "5415905"
        },
        {
            "time": "2025-01-20 02:14:41.430893+08:00",
            "hot_index": "5974612"
        },
        {
            "time": "2025-01-20 02:33:24.127994+08:00",
            "hot_index": "5779861"
        },
        {
            "time": "2025-01-20 02:45:14.081563+08:00",
            "hot_index": "5862328"
        },
        {
            "time": "2025-01-20 03:09:06.022243+08:00",
            "hot_index": "5962478"
        },
        {
            "time": "2025-01-20 03:23:39.746335+08:00",
            "hot_index": "5991027"
        },
        {
            "time": "2025-01-20 03:43:35.673651+08:00",
            "hot_index": "5952205"
        },
        {
            "time": "2025-01-20 04:11:58.732404+08:00",
            "hot_index": "5935601"
        },
        {
            "time": "2025-01-20 04:27:56.486948+08:00",
            "hot_index": "5903533"
        },
        {
            "time": "2025-01-20 04:43:55.614944+08:00",
            "hot_index": "5908074"
        }
    ],
    "女子双眼皮手术4年半后揉出手术针": [
        {
            "time": "2025-01-20 00:13:12.265215+08:00",
            "hot_index": "5819310"
        },
        {
            "time": "2025-01-20 00:33:00.165838+08:00",
            "hot_index": "5600431"
        },
        {
            "time": "2025-01-20 00:43:35.569021+08:00",
            "hot_index": "5772736"
        },
        {
            "time": "2025-01-20 01:10:01.473454+08:00",
            "hot_index": "5864910"
        },
        {
            "time": "2025-01-20 01:28:30.912134+08:00",
            "hot_index": "4734362"
        },
        {
            "time": "2025-01-20 02:14:41.430893+08:00",
            "hot_index": "3120795"
        },
        {
            "time": "2025-01-20 02:33:24.127994+08:00",
            "hot_index": "4620365"
        },
        {
            "time": "2025-01-20 02:45:14.081563+08:00",
            "hot_index": "3394679"
        },
        {
            "time": "2025-01-20 03:09:06.022243+08:00",
            "hot_index": "3787311"
        },
        {
            "time": "2025-01-20 03:23:39.746335+08:00",
            "hot_index": "3427705"
        },
        {
            "time": "2025-01-20 03:43:35.673651+08:00",
            "hot_index": "4022985"
        },
        {
            "time": "2025-01-20 04:11:58.732404+08:00",
            "hot_index": "4447454"
        },
        {
            "time": "2025-01-20 04:27:56.486948+08:00",
            "hot_index": "4428036"
        },
        {
            "time": "2025-01-20 04:43:55.614944+08:00",
            "hot_index": "3976921"
        }
    ],
    "梅德韦杰夫被罚76000美元": [
        {
            "time": "2025-01-20 00:13:12.265215+08:00",
            "hot_index": "5772681"
        },
        {
            "time": "2025-01-20 00:33:00.165838+08:00",
            "hot_index": "6148250"
        },
        {
            "time": "2025-01-20 00:43:35.569021+08:00",
            "hot_index": "6366034"
        },
        {
            "time": "2025-01-20 01:10:01.473454+08:00",
            "hot_index": "5749332"
        },
        {
            "time": "2025-01-20 01:28:30.912134+08:00",
            "hot_index": "4596365"
        },
        {
            "time": "2025-01-20 01:43:50.192560+08:00",
            "hot_index": "4681797"
        },
        {
            "time": "2025-01-20 02:14:41.430893+08:00",
            "hot_index": "5650450"
        },
        {
            "time": "2025-01-20 02:33:24.127994+08:00",
            "hot_index": "5411475"
        },
        {
            "time": "2025-01-20 02:45:14.081563+08:00",
            "hot_index": "6065960"
        },
        {
            "time": "2025-01-20 03:09:06.022243+08:00",
            "hot_index": "6525304"
        },
        {
            "time": "2025-01-20 03:23:39.746335+08:00",
            "hot_index": "5804355"
        },
        {
            "time": "2025-01-20 03:43:35.673651+08:00",
            "hot_index": "4935496"
        },
        {
            "time": "2025-01-20 04:11:58.732404+08:00",
            "hot_index": "4519067"
        },
        {
            "time": "2025-01-20 04:27:56.486948+08:00",
            "hot_index": "5375240"
        },
        {
            "time": "2025-01-20 04:43:55.614944+08:00",
            "hot_index": "5335777"
        }
    ],
    "许七安被抹去了所有痕迹": [
        {
            "time": "2025-01-20 00:13:12.265215+08:00",
            "hot_index": "5616346"
        },
        {
            "time": "2025-01-20 00:33:00.165838+08:00",
            "hot_index": "5821647"
        },
        {
            "time": "2025-01-20 00:43:35.569021+08:00",
            "hot_index": "6088952"
        },
        {
            "time": "2025-01-20 01:10:01.473454+08:00",
            "hot_index": "4441438"
        },
        {
            "time": "2025-01-20 01:28:30.912134+08:00",
            "hot_index": "5467037"
        },
        {
            "time": "2025-01-20 01:43:50.192560+08:00",
            "hot_index": "5315790"
        },
        {
            "time": "2025-01-20 02:14:41.430893+08:00",
            "hot_index": "4581140"
        },
        {
            "time": "2025-01-20 02:33:24.127994+08:00",
            "hot_index": "3696579"
        },
        {
            "time": "2025-01-20 02:45:14.081563+08:00",
            "hot_index": "3467506"
        },
        {
            "time": "2025-01-20 03:09:06.022243+08:00",
            "hot_index": "3579515"
        },
        {
            "time": "2025-01-20 03:23:39.746335+08:00",
            "hot_index": "4214313"
        },
        {
            "time": "2025-01-20 03:43:35.673651+08:00",
            "hot_index": "3199575"
        },
        {
            "time": "2025-01-20 04:27:56.486948+08:00",
            "hot_index": "3431391"
        }
    ],
    "多款手机价格集体降至6000元以内": [
        {
            "time": "2025-01-20 00:13:12.265215+08:00",
            "hot_index": "5547360"
        },
        {
            "time": "2025-01-20 00:33:00.165838+08:00",
            "hot_index": "5303109"
        },
        {
            "time": "2025-01-20 00:43:35.569021+08:00",
            "hot_index": "6277806"
        },
        {
            "time": "2025-01-20 01:10:01.473454+08:00",
            "hot_index": "5925234"
        },
        {
            "time": "2025-01-20 01:28:30.912134+08:00",
            "hot_index": "5157465"
        },
        {
            "time": "2025-01-20 01:43:50.192560+08:00",
            "hot_index": "4953365"
        },
        {
            "time": "2025-01-20 02:14:41.430893+08:00",
            "hot_index": "5748543"
        },
        {
            "time": "2025-01-20 02:33:24.127994+08:00",
            "hot_index": "6057796"
        },
        {
            "time": "2025-01-20 02:45:14.081563+08:00",
            "hot_index": "6156326"
        },
        {
            "time": "2025-01-20 03:09:06.022243+08:00",
            "hot_index": "5454396"
        },
        {
            "time": "2025-01-20 03:23:39.746335+08:00",
            "hot_index": "5530838"
        },
        {
            "time": "2025-01-20 03:43:35.673651+08:00",
            "hot_index": "5089049"
        },
        {
            "time": "2025-01-20 04:11:58.732404+08:00",
            "hot_index": "4988428"
        },
        {
            "time": "2025-01-20 04:27:56.486948+08:00",
            "hot_index": "4856500"
        },
        {
            "time": "2025-01-20 04:43:55.614944+08:00",
            "hot_index": "5134900"
        }
    ],
    "货车货物上摞4辆轿车上高速": [
        {
            "time": "2025-01-20 00:13:12.265215+08:00",
            "hot_index": "5407678"
        },
        {
            "time": "2025-01-20 01:28:30.912134+08:00",
            "hot_index": "6626951"
        },
        {
            "time": "2025-01-20 03:09:06.022243+08:00",
            "hot_index": "5380555"
        },
        {
            "time": "2025-01-20 03:43:35.673651+08:00",
            "hot_index": "6431014"
        },
        {
            "time": "2025-01-20 04:11:58.732404+08:00",
            "hot_index": "5788102"
        },
        {
            "time": "2025-01-20 04:27:56.486948+08:00",
            "hot_index": "5484757"
        },
        {
            "time": "2025-01-20 04:43:55.614944+08:00",
            "hot_index": "5872908"
        }
    ],
    "嫂子喂出嫁小姑子吃面手抖成筛子": [
        {
            "time": "2025-01-20 00:13:12.265215+08:00",
            "hot_index": "5395458"
        },
        {
            "time": "2025-01-20 00:33:00.165838+08:00",
            "hot_index": "5553248"
        },
        {
            "time": "2025-01-20 00:43:35.569021+08:00",
            "hot_index": "5232372"
        },
        {
            "time": "2025-01-20 01:10:01.473454+08:00",
            "hot_index": "5646107"
        },
        {
            "time": "2025-01-20 01:28:30.912134+08:00",
            "hot_index": "5713400"
        },
        {
            "time": "2025-01-20 01:43:50.192560+08:00",
            "hot_index": "5265933"
        },
        {
            "time": "2025-01-20 02:14:41.430893+08:00",
            "hot_index": "5539680"
        },
        {
            "time": "2025-01-20 02:33:24.127994+08:00",
            "hot_index": "5372487"
        },
        {
            "time": "2025-01-20 02:45:14.081563+08:00",
            "hot_index": "5319727"
        },
        {
            "time": "2025-01-20 03:09:06.022243+08:00",
            "hot_index": "5265902"
        },
        {
            "time": "2025-01-20 03:23:39.746335+08:00",
            "hot_index": "5183020"
        },
        {
            "time": "2025-01-20 03:43:35.673651+08:00",
            "hot_index": "5235837"
        },
        {
            "time": "2025-01-20 04:11:58.732404+08:00",
            "hot_index": "5172022"
        },
        {
            "time": "2025-01-20 04:27:56.486948+08:00",
            "hot_index": "5605850"
        },
        {
            "time": "2025-01-20 04:43:55.614944+08:00",
            "hot_index": "5500293"
        }
    ],
    "一家五人先后确诊同一种癌": [
        {
            "time": "2025-01-20 00:13:12.265215+08:00",
            "hot_index": "5232442"
        },
        {
            "time": "2025-01-20 00:33:00.165838+08:00",
            "hot_index": "5167912"
        },
        {
            "time": "2025-01-20 00:43:35.569021+08:00",
            "hot_index": "4744867"
        },
        {
            "time": "2025-01-20 01:10:01.473454+08:00",
            "hot_index": "3408674"
        },
        {
            "time": "2025-01-20 01:28:30.912134+08:00",
            "hot_index": "3465320"
        },
        {
            "time": "2025-01-20 01:43:50.192560+08:00",
            "hot_index": "3696224"
        },
        {
            "time": "2025-01-20 02:14:41.430893+08:00",
            "hot_index": "3913697"
        },
        {
            "time": "2025-01-20 02:33:24.127994+08:00",
            "hot_index": "3761582"
        },
        {
            "time": "2025-01-20 02:45:14.081563+08:00",
            "hot_index": "4096552"
        },
        {
            "time": "2025-01-20 03:09:06.022243+08:00",
            "hot_index": "4193640"
        },
        {
            "time": "2025-01-20 03:23:39.746335+08:00",
            "hot_index": "4700963"
        },
        {
            "time": "2025-01-20 03:43:35.673651+08:00",
            "hot_index": "5647407"
        },
        {
            "time": "2025-01-20 04:11:58.732404+08:00",
            "hot_index": "5374684"
        },
        {
            "time": "2025-01-20 04:27:56.486948+08:00",
            "hot_index": "4531456"
        },
        {
            "time": "2025-01-20 04:43:55.614944+08:00",
            "hot_index": "5414848"
        }
    ],
    "狗狗踩在女生身上“滑雪”": [
        {
            "time": "2025-01-20 00:13:12.265215+08:00",
            "hot_index": "5192066"
        },
        {
            "time": "2025-01-20 00:33:00.165838+08:00",
            "hot_index": "4930092"
        },
        {
            "time": "2025-01-20 00:43:35.569021+08:00",
            "hot_index": "5058554"
        },
        {
            "time": "2025-01-20 01:10:01.473454+08:00",
            "hot_index": "4130617"
        },
        {
            "time": "2025-01-20 01:28:30.912134+08:00",
            "hot_index": "3100000"
        },
        {
            "time": "2025-01-20 01:43:50.192560+08:00",
            "hot_index": "3450876"
        },
        {
            "time": "2025-01-20 02:14:41.430893+08:00",
            "hot_index": "4058983"
        },
        {
            "time": "2025-01-20 02:33:24.127994+08:00",
            "hot_index": "3529733"
        },
        {
            "time": "2025-01-20 04:43:55.614944+08:00",
            "hot_index": "6298390"
        }
    ],
    "会钓鱼的和不会钓鱼的都沉默了": [
        {
            "time": "2025-01-20 00:13:12.265215+08:00",
            "hot_index": "5043788"
        },
        {
            "time": "2025-01-20 00:33:00.165838+08:00",
            "hot_index": "4705337"
        },
        {
            "time": "2025-01-20 00:43:35.569021+08:00",
            "hot_index": "4647535"
        },
        {
            "time": "2025-01-20 01:10:01.473454+08:00",
            "hot_index": "3874725"
        },
        {
            "time": "2025-01-20 01:28:30.912134+08:00",
            "hot_index": "3592381"
        },
        {
            "time": "2025-01-20 01:43:50.192560+08:00",
            "hot_index": "3721254"
        },
        {
            "time": "2025-01-20 02:14:41.430893+08:00",
            "hot_index": "5430603"
        },
        {
            "time": "2025-01-20 02:33:24.127994+08:00",
            "hot_index": "5145731"
        },
        {
            "time": "2025-01-20 02:45:14.081563+08:00",
            "hot_index": "5764832"
        },
        {
            "time": "2025-01-20 03:09:06.022243+08:00",
            "hot_index": "5610242"
        },
        {
            "time": "2025-01-20 03:23:39.746335+08:00",
            "hot_index": "6219381"
        },
        {
            "time": "2025-01-20 03:43:35.673651+08:00",
            "hot_index": "5860895"
        },
        {
            "time": "2025-01-20 04:11:58.732404+08:00",
            "hot_index": "5623809"
        },
        {
            "time": "2025-01-20 04:27:56.486948+08:00",
            "hot_index": "6058955"
        },
        {
            "time": "2025-01-20 04:43:55.614944+08:00",
            "hot_index": "5085254"
        }
    ],
    "贾宝玉真的从书里走出来了": [
        {
            "time": "2025-01-20 00:13:12.265215+08:00",
            "hot_index": "4983584"
        },
        {
            "time": "2025-01-20 00:33:00.165838+08:00",
            "hot_index": "4313291"
        },
        {
            "time": "2025-01-20 00:43:35.569021+08:00",
            "hot_index": "4039254"
        },
        {
            "time": "2025-01-20 01:28:30.912134+08:00",
            "hot_index": "3153251"
        },
        {
            "time": "2025-01-20 01:43:50.192560+08:00",
            "hot_index": "3863126"
        },
        {
            "time": "2025-01-20 02:14:41.430893+08:00",
            "hot_index": "4355304"
        },
        {
            "time": "2025-01-20 02:33:24.127994+08:00",
            "hot_index": "4275851"
        },
        {
            "time": "2025-01-20 02:45:14.081563+08:00",
            "hot_index": "4136876"
        },
        {
            "time": "2025-01-20 03:09:06.022243+08:00",
            "hot_index": "4049983"
        },
        {
            "time": "2025-01-20 03:23:39.746335+08:00",
            "hot_index": "4132547"
        },
        {
            "time": "2025-01-20 03:43:35.673651+08:00",
            "hot_index": "3267346"
        },
        {
            "time": "2025-01-20 04:11:58.732404+08:00",
            "hot_index": "4807765"
        },
        {
            "time": "2025-01-20 04:27:56.486948+08:00",
            "hot_index": "4793582"
        },
        {
            "time": "2025-01-20 04:43:55.614944+08:00",
            "hot_index": "3842045"
        }
    ],
    "赵雅芝蛇年春晚好忙": [
        {
            "time": "2025-01-20 00:13:12.265215+08:00",
            "hot_index": "4872432"
        },
        {
            "time": "2025-01-20 00:33:00.165838+08:00",
            "hot_index": "4855243"
        },
        {
            "time": "2025-01-20 00:43:35.569021+08:00",
            "hot_index": "4832007"
        },
        {
            "time": "2025-01-20 01:10:01.473454+08:00",
            "hot_index": "4587817"
        },
        {
            "time": "2025-01-20 01:43:50.192560+08:00",
            "hot_index": "3920055"
        },
        {
            "time": "2025-01-20 02:45:14.081563+08:00",
            "hot_index": "3261702"
        },
        {
            "time": "2025-01-20 03:09:06.022243+08:00",
            "hot_index": "4477507"
        },
        {
            "time": "2025-01-20 03:23:39.746335+08:00",
            "hot_index": "3875513"
        },
        {
            "time": "2025-01-20 04:11:58.732404+08:00",
            "hot_index": "4217378"
        }
    ],
    "别等油冒烟了再炒菜": [
        {
            "time": "2025-01-20 00:13:12.265215+08:00",
            "hot_index": "4721250"
        },
        {
            "time": "2025-01-20 00:33:00.165838+08:00",
            "hot_index": "4269830"
        },
        {
            "time": "2025-01-20 00:43:35.569021+08:00",
            "hot_index": "4299674"
        },
        {
            "time": "2025-01-20 01:28:30.912134+08:00",
            "hot_index": "3259176"
        },
        {
            "time": "2025-01-20 01:43:50.192560+08:00",
            "hot_index": "3100000"
        },
        {
            "time": "2025-01-20 02:14:41.430893+08:00",
            "hot_index": "3279224"
        },
        {
            "time": "2025-01-20 02:33:24.127994+08:00",
            "hot_index": "4132251"
        },
        {
            "time": "2025-01-20 02:45:14.081563+08:00",
            "hot_index": "5012985"
        },
        {
            "time": "2025-01-20 03:23:39.746335+08:00",
            "hot_index": "3125281"
        },
        {
            "time": "2025-01-20 03:43:35.673651+08:00",
            "hot_index": "3559897"
        },
        {
            "time": "2025-01-20 04:11:58.732404+08:00",
            "hot_index": "3344251"
        },
        {
            "time": "2025-01-20 04:27:56.486948+08:00",
            "hot_index": "4644894"
        },
        {
            "time": "2025-01-20 04:43:55.614944+08:00",
            "hot_index": "3317767"
        }
    ],
    "吴艳妮晒肯豆风写真": [
        {
            "time": "2025-01-20 00:13:12.265215+08:00",
            "hot_index": "4696849"
        },
        {
            "time": "2025-01-20 00:33:00.165838+08:00",
            "hot_index": "3919340"
        },
        {
            "time": "2025-01-20 00:43:35.569021+08:00",
            "hot_index": "3986766"
        },
        {
            "time": "2025-01-20 01:10:01.473454+08:00",
            "hot_index": "3391425"
        },
        {
            "time": "2025-01-20 01:28:30.912134+08:00",
            "hot_index": "4908735"
        },
        {
            "time": "2025-01-20 01:43:50.192560+08:00",
            "hot_index": "5913119"
        },
        {
            "time": "2025-01-20 02:14:41.430893+08:00",
            "hot_index": "6386683"
        },
        {
            "time": "2025-01-20 02:33:24.127994+08:00",
            "hot_index": "6164711"
        },
        {
            "time": "2025-01-20 02:45:14.081563+08:00",
            "hot_index": "6209946"
        },
        {
            "time": "2025-01-20 03:09:06.022243+08:00",
            "hot_index": "5503112"
        },
        {
            "time": "2025-01-20 03:23:39.746335+08:00",
            "hot_index": "5601474"
        },
        {
            "time": "2025-01-20 03:43:35.673651+08:00",
            "hot_index": "6021479"
        },
        {
            "time": "2025-01-20 04:11:58.732404+08:00",
            "hot_index": "5521597"
        },
        {
            "time": "2025-01-20 04:27:56.486948+08:00",
            "hot_index": "5114467"
        },
        {
            "time": "2025-01-20 04:43:55.614944+08:00",
            "hot_index": "5288774"
        }
    ],
    "数百宝妈串手串赚代工费被骗超百万": [
        {
            "time": "2025-01-20 00:13:12.265215+08:00",
            "hot_index": "4526981"
        },
        {
            "time": "2025-01-20 00:33:00.165838+08:00",
            "hot_index": "4134252"
        },
        {
            "time": "2025-01-20 00:43:35.569021+08:00",
            "hot_index": "3899653"
        },
        {
            "time": "2025-01-20 01:10:01.473454+08:00",
            "hot_index": "4271552"
        },
        {
            "time": "2025-01-20 01:28:30.912134+08:00",
            "hot_index": "3889476"
        },
        {
            "time": "2025-01-20 01:43:50.192560+08:00",
            "hot_index": "3215281"
        },
        {
            "time": "2025-01-20 02:14:41.430893+08:00",
            "hot_index": "3545189"
        },
        {
            "time": "2025-01-20 02:33:24.127994+08:00",
            "hot_index": "3300943"
        },
        {
            "time": "2025-01-20 02:45:14.081563+08:00",
            "hot_index": "3718787"
        },
        {
            "time": "2025-01-20 03:23:39.746335+08:00",
            "hot_index": "3326065"
        },
        {
            "time": "2025-01-20 03:43:35.673651+08:00",
            "hot_index": "3362577"
        },
        {
            "time": "2025-01-20 04:27:56.486948+08:00",
            "hot_index": "3720801"
        },
        {
            "time": "2025-01-20 04:43:55.614944+08:00",
            "hot_index": "3100000"
        }
    ],
    "美网友：美国人终于知道中国有多美": [
        {
            "time": "2025-01-20 00:13:12.265215+08:00",
            "hot_index": "4453345"
        },
        {
            "time": "2025-01-20 00:33:00.165838+08:00",
            "hot_index": "3831604"
        },
        {
            "time": "2025-01-20 00:43:35.569021+08:00",
            "hot_index": "4111656"
        },
        {
            "time": "2025-01-20 01:10:01.473454+08:00",
            "hot_index": "3181661"
        },
        {
            "time": "2025-01-20 01:28:30.912134+08:00",
            "hot_index": "4391186"
        },
        {
            "time": "2025-01-20 01:43:50.192560+08:00",
            "hot_index": "4820570"
        },
        {
            "time": "2025-01-20 02:14:41.430893+08:00",
            "hot_index": "4275877"
        },
        {
            "time": "2025-01-20 02:33:24.127994+08:00",
            "hot_index": "3449227"
        },
        {
            "time": "2025-01-20 02:45:14.081563+08:00",
            "hot_index": "3828613"
        },
        {
            "time": "2025-01-20 03:09:06.022243+08:00",
            "hot_index": "3812912"
        },
        {
            "time": "2025-01-20 03:23:39.746335+08:00",
            "hot_index": "4641248"
        },
        {
            "time": "2025-01-20 04:11:58.732404+08:00",
            "hot_index": "3185679"
        },
        {
            "time": "2025-01-20 04:27:56.486948+08:00",
            "hot_index": "4222442"
        },
        {
            "time": "2025-01-20 04:43:55.614944+08:00",
            "hot_index": "4907226"
        }
    ],
    "全世界都在做鸡蛋羹": [
        {
            "time": "2025-01-20 00:13:12.265215+08:00",
            "hot_index": "4393008"
        },
        {
            "time": "2025-01-20 00:33:00.165838+08:00",
            "hot_index": "3742812"
        },
        {
            "time": "2025-01-20 00:43:35.569021+08:00",
            "hot_index": "3732160"
        },
        {
            "time": "2025-01-20 01:28:30.912134+08:00",
            "hot_index": "3668652"
        },
        {
            "time": "2025-01-20 01:43:50.192560+08:00",
            "hot_index": "3137626"
        },
        {
            "time": "2025-01-20 02:14:41.430893+08:00",
            "hot_index": "3406466"
        },
        {
            "time": "2025-01-20 02:33:24.127994+08:00",
            "hot_index": "3905385"
        },
        {
            "time": "2025-01-20 02:45:14.081563+08:00",
            "hot_index": "4221702"
        },
        {
            "time": "2025-01-20 03:09:06.022243+08:00",
            "hot_index": "3465728"
        },
        {
            "time": "2025-01-20 03:23:39.746335+08:00",
            "hot_index": "3563202"
        },
        {
            "time": "2025-01-20 03:43:35.673651+08:00",
            "hot_index": "3676577"
        },
        {
            "time": "2025-01-20 04:11:58.732404+08:00",
            "hot_index": "3100000"
        },
        {
            "time": "2025-01-20 04:27:56.486948+08:00",
            "hot_index": "3665834"
        }
    ],
    "山东鹤伴山景区遭野猴袭扰": [
        {
            "time": "2025-01-20 00:13:12.265215+08:00",
            "hot_index": "4297406"
        },
        {
            "time": "2025-01-20 01:28:30.912134+08:00",
            "hot_index": "6527371"
        },
        {
            "time": "2025-01-20 03:43:35.673651+08:00",
            "hot_index": "3767446"
        }
    ],
    "高压锅放过赵今麦吧": [
        {
            "time": "2025-01-20 00:13:12.265215+08:00",
            "hot_index": "4143173"
        },
        {
            "time": "2025-01-20 00:33:00.165838+08:00",
            "hot_index": "4036008"
        },
        {
            "time": "2025-01-20 00:43:35.569021+08:00",
            "hot_index": "4392175"
        },
        {
            "time": "2025-01-20 01:10:01.473454+08:00",
            "hot_index": "4097756"
        },
        {
            "time": "2025-01-20 01:28:30.912134+08:00",
            "hot_index": "4068231"
        },
        {
            "time": "2025-01-20 01:43:50.192560+08:00",
            "hot_index": "4002964"
        },
        {
            "time": "2025-01-20 02:14:41.430893+08:00",
            "hot_index": "4167081"
        },
        {
            "time": "2025-01-20 02:33:24.127994+08:00",
            "hot_index": "5213364"
        },
        {
            "time": "2025-01-20 02:45:14.081563+08:00",
            "hot_index": "4321636"
        },
        {
            "time": "2025-01-20 03:09:06.022243+08:00",
            "hot_index": "4687274"
        },
        {
            "time": "2025-01-20 03:23:39.746335+08:00",
            "hot_index": "4310987"
        },
        {
            "time": "2025-01-20 03:43:35.673651+08:00",
            "hot_index": "4622909"
        },
        {
            "time": "2025-01-20 04:11:58.732404+08:00",
            "hot_index": "4039657"
        },
        {
            "time": "2025-01-20 04:27:56.486948+08:00",
            "hot_index": "4015865"
        },
        {
            "time": "2025-01-20 04:43:55.614944+08:00",
            "hot_index": "4090868"
        }
    ],
    "美国网友在线为TikTok办葬礼": [
        {
            "time": "2025-01-20 00:13:12.265215+08:00",
            "hot_index": "4039005"
        },
        {
            "time": "2025-01-20 00:33:00.165838+08:00",
            "hot_index": "4507228"
        },
        {
            "time": "2025-01-20 00:43:35.569021+08:00",
            "hot_index": "5428793"
        },
        {
            "time": "2025-01-20 01:10:01.473454+08:00",
            "hot_index": "5394666"
        },
        {
            "time": "2025-01-20 01:28:30.912134+08:00",
            "hot_index": "5892658"
        },
        {
            "time": "2025-01-20 01:43:50.192560+08:00",
            "hot_index": "6106693"
        },
        {
            "time": "2025-01-20 02:14:41.430893+08:00",
            "hot_index": "6283225"
        },
        {
            "time": "2025-01-20 02:33:24.127994+08:00",
            "hot_index": "5659231"
        },
        {
            "time": "2025-01-20 02:45:14.081563+08:00",
            "hot_index": "5612951"
        },
        {
            "time": "2025-01-20 03:09:06.022243+08:00",
            "hot_index": "6199730"
        },
        {
            "time": "2025-01-20 03:23:39.746335+08:00",
            "hot_index": "5716856"
        },
        {
            "time": "2025-01-20 03:43:35.673651+08:00",
            "hot_index": "6378763"
        },
        {
            "time": "2025-01-20 04:11:58.732404+08:00",
            "hot_index": "6099402"
        },
        {
            "time": "2025-01-20 04:27:56.486948+08:00",
            "hot_index": "6271477"
        },
        {
            "time": "2025-01-20 04:43:55.614944+08:00",
            "hot_index": "6730517"
        }
    ],
    "《射雕英雄传》预售破1000万": [
        {
            "time": "2025-01-20 00:13:12.265215+08:00",
            "hot_index": "3944466"
        },
        {
            "time": "2025-01-20 00:33:00.165838+08:00",
            "hot_index": "3645867"
        },
        {
            "time": "2025-01-20 00:43:35.569021+08:00",
            "hot_index": "4589689"
        },
        {
            "time": "2025-01-20 01:10:01.473454+08:00",
            "hot_index": "4627810"
        },
        {
            "time": "2025-01-20 01:28:30.912134+08:00",
            "hot_index": "5956060"
        },
        {
            "time": "2025-01-20 01:43:50.192560+08:00",
            "hot_index": "4714543"
        },
        {
            "time": "2025-01-20 02:14:41.430893+08:00",
            "hot_index": "4754683"
        },
        {
            "time": "2025-01-20 02:33:24.127994+08:00",
            "hot_index": "4983614"
        },
        {
            "time": "2025-01-20 02:45:14.081563+08:00",
            "hot_index": "5128036"
        },
        {
            "time": "2025-01-20 03:09:06.022243+08:00",
            "hot_index": "4505036"
        },
        {
            "time": "2025-01-20 03:23:39.746335+08:00",
            "hot_index": "4409531"
        },
        {
            "time": "2025-01-20 03:43:35.673651+08:00",
            "hot_index": "4267274"
        },
        {
            "time": "2025-01-20 04:11:58.732404+08:00",
            "hot_index": "3823076"
        },
        {
            "time": "2025-01-20 04:27:56.486948+08:00",
            "hot_index": "3202659"
        }
    ],
    "小孩高铁上吵闹被怒吼": [
        {
            "time": "2025-01-20 00:13:12.265215+08:00",
            "hot_index": "3824665"
        },
        {
            "time": "2025-01-20 00:33:00.165838+08:00",
            "hot_index": "3304510"
        },
        {
            "time": "2025-01-20 00:43:35.569021+08:00",
            "hot_index": "6113676"
        },
        {
            "time": "2025-01-20 01:10:01.473454+08:00",
            "hot_index": "3763183"
        },
        {
            "time": "2025-01-20 01:28:30.912134+08:00",
            "hot_index": "4230774"
        },
        {
            "time": "2025-01-20 01:43:50.192560+08:00",
            "hot_index": "4372292"
        },
        {
            "time": "2025-01-20 02:14:41.430893+08:00",
            "hot_index": "3340187"
        },
        {
            "time": "2025-01-20 02:33:24.127994+08:00",
            "hot_index": "3839147"
        },
        {
            "time": "2025-01-20 02:45:14.081563+08:00",
            "hot_index": "3634691"
        },
        {
            "time": "2025-01-20 03:09:06.022243+08:00",
            "hot_index": "3605549"
        },
        {
            "time": "2025-01-20 03:23:39.746335+08:00",
            "hot_index": "3968626"
        },
        {
            "time": "2025-01-20 04:27:56.486948+08:00",
            "hot_index": "3383108"
        }
    ],
    "美媒称“加州大火因为中国人”遭批": [
        {
            "time": "2025-01-20 00:13:12.265215+08:00",
            "hot_index": "3770316"
        },
        {
            "time": "2025-01-20 00:43:35.569021+08:00",
            "hot_index": "4452771"
        },
        {
            "time": "2025-01-20 01:28:30.912134+08:00",
            "hot_index": "3710637"
        },
        {
            "time": "2025-01-20 02:33:24.127994+08:00",
            "hot_index": "4711655"
        },
        {
            "time": "2025-01-20 03:09:06.022243+08:00",
            "hot_index": "4819024"
        },
        {
            "time": "2025-01-20 03:43:35.673651+08:00",
            "hot_index": "4767656"
        },
        {
            "time": "2025-01-20 04:11:58.732404+08:00",
            "hot_index": "5460645"
        },
        {
            "time": "2025-01-20 04:27:56.486948+08:00",
            "hot_index": "3995013"
        },
        {
            "time": "2025-01-20 04:43:55.614944+08:00",
            "hot_index": "4774275"
        }
    ],
    "吴尊女儿neinei14岁近照曝光": [
        {
            "time": "2025-01-20 00:13:12.265215+08:00",
            "hot_index": "3648825"
        },
        {
            "time": "2025-01-20 00:43:35.569021+08:00",
            "hot_index": "3306282"
        },
        {
            "time": "2025-01-20 01:10:01.473454+08:00",
            "hot_index": "3554962"
        },
        {
            "time": "2025-01-20 01:28:30.912134+08:00",
            "hot_index": "4193618"
        },
        {
            "time": "2025-01-20 02:14:41.430893+08:00",
            "hot_index": "3653042"
        },
        {
            "time": "2025-01-20 02:33:24.127994+08:00",
            "hot_index": "4875959"
        },
        {
            "time": "2025-01-20 02:45:14.081563+08:00",
            "hot_index": "4989550"
        }
    ],
    "公安厅副厅长61岁把自己送进监狱": [
        {
            "time": "2025-01-20 00:13:12.265215+08:00",
            "hot_index": "3540123"
        },
        {
            "time": "2025-01-20 00:33:00.165838+08:00",
            "hot_index": "3105302"
        },
        {
            "time": "2025-01-20 01:10:01.473454+08:00",
            "hot_index": "4358890"
        },
        {
            "time": "2025-01-20 01:28:30.912134+08:00",
            "hot_index": "4882874"
        },
        {
            "time": "2025-01-20 02:14:41.430893+08:00",
            "hot_index": "3788945"
        },
        {
            "time": "2025-01-20 02:33:24.127994+08:00",
            "hot_index": "5022767"
        },
        {
            "time": "2025-01-20 02:45:14.081563+08:00",
            "hot_index": "4451407"
        },
        {
            "time": "2025-01-20 03:09:06.022243+08:00",
            "hot_index": "3915058"
        },
        {
            "time": "2025-01-20 03:23:39.746335+08:00",
            "hot_index": "4813265"
        },
        {
            "time": "2025-01-20 03:43:35.673651+08:00",
            "hot_index": "4302416"
        },
        {
            "time": "2025-01-20 04:11:58.732404+08:00",
            "hot_index": "3660639"
        },
        {
            "time": "2025-01-20 04:27:56.486948+08:00",
            "hot_index": "3509761"
        },
        {
            "time": "2025-01-20 04:43:55.614944+08:00",
            "hot_index": "3596719"
        }
    ],
    "国家一级演员邬丽因病去世": [
        {
            "time": "2025-01-20 00:13:12.265215+08:00",
            "hot_index": "3492005"
        },
        {
            "time": "2025-01-20 00:33:00.165838+08:00",
            "hot_index": "3100000"
        },
        {
            "time": "2025-01-20 00:43:35.569021+08:00",
            "hot_index": "3117206"
        },
        {
            "time": "2025-01-20 01:10:01.473454+08:00",
            "hot_index": "6534506"
        },
        {
            "time": "2025-01-20 01:28:30.912134+08:00",
            "hot_index": "6108532"
        },
        {
            "time": "2025-01-20 02:14:41.430893+08:00",
            "hot_index": "4466767"
        },
        {
            "time": "2025-01-20 02:33:24.127994+08:00",
            "hot_index": "6635549"
        },
        {
            "time": "2025-01-20 02:45:14.081563+08:00",
            "hot_index": "6416023"
        },
        {
            "time": "2025-01-20 03:09:06.022243+08:00",
            "hot_index": "3340412"
        },
        {
            "time": "2025-01-20 03:23:39.746335+08:00",
            "hot_index": "4098522"
        },
        {
            "time": "2025-01-20 03:43:35.673651+08:00",
            "hot_index": "5566739"
        },
        {
            "time": "2025-01-20 04:11:58.732404+08:00",
            "hot_index": "6603340"
        },
        {
            "time": "2025-01-20 04:27:56.486948+08:00",
            "hot_index": "6620439"
        },
        {
            "time": "2025-01-20 04:43:55.614944+08:00",
            "hot_index": "6510721"
        }
    ],
    "中国穿越机百公里加速时间不到1秒": [
        {
            "time": "2025-01-20 00:13:12.265215+08:00",
            "hot_index": "3307351"
        },
        {
            "time": "2025-01-20 02:33:24.127994+08:00",
            "hot_index": "5895298"
        },
        {
            "time": "2025-01-20 03:43:35.673651+08:00",
            "hot_index": "6521470"
        }
    ],
    "为什么越来越多城市选择小公交": [
        {
            "time": "2025-01-20 00:13:12.265215+08:00",
            "hot_index": "3267673"
        },
        {
            "time": "2025-01-20 00:33:00.165838+08:00",
            "hot_index": "3563892"
        },
        {
            "time": "2025-01-20 00:43:35.569021+08:00",
            "hot_index": "3264457"
        },
        {
            "time": "2025-01-20 01:10:01.473454+08:00",
            "hot_index": "3100000"
        },
        {
            "time": "2025-01-20 01:28:30.912134+08:00",
            "hot_index": "5297673"
        },
        {
            "time": "2025-01-20 01:43:50.192560+08:00",
            "hot_index": "3375551"
        },
        {
            "time": "2025-01-20 02:33:24.127994+08:00",
            "hot_index": "3206482"
        },
        {
            "time": "2025-01-20 03:09:06.022243+08:00",
            "hot_index": "4238760"
        },
        {
            "time": "2025-01-20 03:43:35.673651+08:00",
            "hot_index": "3473489"
        },
        {
            "time": "2025-01-20 04:11:58.732404+08:00",
            "hot_index": "6550151"
        },
        {
            "time": "2025-01-20 04:43:55.614944+08:00",
            "hot_index": "3454247"
        }
    ],
    "美国网友已经准备在屋前屋后种菜": [
        {
            "time": "2025-01-20 00:13:12.265215+08:00",
            "hot_index": "3180468"
        },
        {
            "time": "2025-01-20 00:33:00.165838+08:00",
            "hot_index": "5219283"
        },
        {
            "time": "2025-01-20 00:43:35.569021+08:00",
            "hot_index": "5874888"
        },
        {
            "time": "2025-01-20 01:10:01.473454+08:00",
            "hot_index": "5283602"
        },
        {
            "time": "2025-01-20 01:28:30.912134+08:00",
            "hot_index": "4610636"
        },
        {
            "time": "2025-01-20 01:43:50.192560+08:00",
            "hot_index": "5539607"
        },
        {
            "time": "2025-01-20 02:14:41.430893+08:00",
            "hot_index": "5336885"
        },
        {
            "time": "2025-01-20 02:33:24.127994+08:00",
            "hot_index": "4065240"
        },
        {
            "time": "2025-01-20 02:45:14.081563+08:00",
            "hot_index": "4727863"
        },
        {
            "time": "2025-01-20 03:09:06.022243+08:00",
            "hot_index": "5152772"
        },
        {
            "time": "2025-01-20 03:23:39.746335+08:00",
            "hot_index": "4555772"
        },
        {
            "time": "2025-01-20 03:43:35.673651+08:00",
            "hot_index": "3841865"
        },
        {
            "time": "2025-01-20 04:11:58.732404+08:00",
            "hot_index": "3906371"
        },
        {
            "time": "2025-01-20 04:27:56.486948+08:00",
            "hot_index": "4983491"
        },
        {
            "time": "2025-01-20 04:43:55.614944+08:00",
            "hot_index": "4482768"
        }
    ],
    "没人能顺利念出大风车这句歌词": [
        {
            "time": "2025-01-20 00:13:12.265215+08:00",
            "hot_index": "3100000"
        },
        {
            "time": "2025-01-20 00:33:00.165838+08:00",
            "hot_index": "3487258"
        },
        {
            "time": "2025-01-20 00:43:35.569021+08:00",
            "hot_index": "5199573"
        },
        {
            "time": "2025-01-20 01:10:01.473454+08:00",
            "hot_index": "4844709"
        },
        {
            "time": "2025-01-20 02:14:41.430893+08:00",
            "hot_index": "3846464"
        },
        {
            "time": "2025-01-20 03:09:06.022243+08:00",
            "hot_index": "3105859"
        },
        {
            "time": "2025-01-20 04:11:58.732404+08:00",
            "hot_index": "3214072"
        },
        {
            "time": "2025-01-20 04:43:55.614944+08:00",
            "hot_index": "3293820"
        }
    ],
    "陈丽君第一部原创大戏首演": [
        {
            "time": "2025-01-20 00:33:00.165838+08:00",
            "hot_index": "6780809"
        }
    ],
    "夏弃疾不再接任何艺人商业约拍": [
        {
            "time": "2025-01-20 00:33:00.165838+08:00",
            "hot_index": "6610875"
        }
    ],
    "山东或将换上山西同款赛博外墙": [
        {
            "time": "2025-01-20 00:33:00.165838+08:00",
            "hot_index": "6518272"
        }
    ],
    "牺牲军人陈艳阳骨灰安葬仪式举行": [
        {
            "time": "2025-01-20 00:33:00.165838+08:00",
            "hot_index": "6387648"
        },
        {
            "time": "2025-01-20 01:43:50.192560+08:00",
            "hot_index": "6709155"
        }
    ],
    "12岁哥哥摆摊卖小米为白血病妹妹筹钱": [
        {
            "time": "2025-01-20 00:33:00.165838+08:00",
            "hot_index": "6298398"
        },
        {
            "time": "2025-01-20 01:43:50.192560+08:00",
            "hot_index": "6376726"
        }
    ],
    "何小鹏在年会为员工抽奖送车": [
        {
            "time": "2025-01-20 00:33:00.165838+08:00",
            "hot_index": "5431111"
        },
        {
            "time": "2025-01-20 01:43:50.192560+08:00",
            "hot_index": "5149079"
        }
    ],
    "男子参加婚礼吃席中途被告知吃错席": [
        {
            "time": "2025-01-20 00:33:00.165838+08:00",
            "hot_index": "5089045"
        },
        {
            "time": "2025-01-20 02:14:41.430893+08:00",
            "hot_index": "6162334"
        },
        {
            "time": "2025-01-20 02:45:14.081563+08:00",
            "hot_index": "3111964"
        },
        {
            "time": "2025-01-20 03:23:39.746335+08:00",
            "hot_index": "6776648"
        },
        {
            "time": "2025-01-20 04:43:55.614944+08:00",
            "hot_index": "5695788"
        }
    ],
    "女子假扮机器人回村被介绍对象": [
        {
            "time": "2025-01-20 00:33:00.165838+08:00",
            "hot_index": "3277457"
        },
        {
            "time": "2025-01-20 01:43:50.192560+08:00",
            "hot_index": "6464825"
        }
    ],
    "2024年中国经济第一大省悬念揭晓": [
        {
            "time": "2025-01-20 00:43:35.569021+08:00",
            "hot_index": "7200889"
        },
        {
            "time": "2025-01-20 01:10:01.473454+08:00",
            "hot_index": "7255161"
        },
        {
            "time": "2025-01-20 01:28:30.912134+08:00",
            "hot_index": "7203180"
        },
        {
            "time": "2025-01-20 01:43:50.192560+08:00",
            "hot_index": "7211122"
        },
        {
            "time": "2025-01-20 02:14:41.430893+08:00",
            "hot_index": "7290854"
        },
        {
            "time": "2025-01-20 02:33:24.127994+08:00",
            "hot_index": "7244065"
        },
        {
            "time": "2025-01-20 02:45:14.081563+08:00",
            "hot_index": "7203035"
        },
        {
            "time": "2025-01-20 03:09:06.022243+08:00",
            "hot_index": "7225099"
        },
        {
            "time": "2025-01-20 03:23:39.746335+08:00",
            "hot_index": "7294469"
        },
        {
            "time": "2025-01-20 03:43:35.673651+08:00",
            "hot_index": "7215040"
        },
        {
            "time": "2025-01-20 04:11:58.732404+08:00",
            "hot_index": "7224020"
        },
        {
            "time": "2025-01-20 04:27:56.486948+08:00",
            "hot_index": "7287047"
        },
        {
            "time": "2025-01-20 04:43:55.614944+08:00",
            "hot_index": "7277802"
        }
    ],
    "46岁华人出任日乒女队主教练": [
        {
            "time": "2025-01-20 00:43:35.569021+08:00",
            "hot_index": "6727808"
        },
        {
            "time": "2025-01-20 02:45:14.081563+08:00",
            "hot_index": "3100000"
        },
        {
            "time": "2025-01-20 03:09:06.022243+08:00",
            "hot_index": "6254591"
        },
        {
            "time": "2025-01-20 03:23:39.746335+08:00",
            "hot_index": "5226211"
        },
        {
            "time": "2025-01-20 03:43:35.673651+08:00",
            "hot_index": "4883136"
        },
        {
            "time": "2025-01-20 04:11:58.732404+08:00",
            "hot_index": "5835063"
        },
        {
            "time": "2025-01-20 04:27:56.486948+08:00",
            "hot_index": "5044299"
        },
        {
            "time": "2025-01-20 04:43:55.614944+08:00",
            "hot_index": "4206700"
        }
    ],
    "腿友们断骨增高结果像一场赌博": [
        {
            "time": "2025-01-20 00:43:35.569021+08:00",
            "hot_index": "6626997"
        }
    ],
    "坐火车如何快速找到充电口": [
        {
            "time": "2025-01-20 00:43:35.569021+08:00",
            "hot_index": "5655684"
        }
    ],
    "上海GDP超5万亿意味着什么": [
        {
            "time": "2025-01-20 00:43:35.569021+08:00",
            "hot_index": "5585766"
        }
    ],
    "23日起强冷空气携雨雪降温来袭": [
        {
            "time": "2025-01-20 00:43:35.569021+08:00",
            "hot_index": "4932265"
        },
        {
            "time": "2025-01-20 01:43:50.192560+08:00",
            "hot_index": "5878204"
        }
    ],
    "别墅区疑占10个足球场大公共绿地": [
        {
            "time": "2025-01-20 00:43:35.569021+08:00",
            "hot_index": "3566656"
        }
    ],
    "骗子转走300万给受害人转1万做生活费": [
        {
            "time": "2025-01-20 00:43:35.569021+08:00",
            "hot_index": "3417765"
        },
        {
            "time": "2025-01-20 01:10:01.473454+08:00",
            "hot_index": "6605311"
        },
        {
            "time": "2025-01-20 01:28:30.912134+08:00",
            "hot_index": "6792014"
        },
        {
            "time": "2025-01-20 01:43:50.192560+08:00",
            "hot_index": "6630849"
        },
        {
            "time": "2025-01-20 02:14:41.430893+08:00",
            "hot_index": "6594830"
        },
        {
            "time": "2025-01-20 02:33:24.127994+08:00",
            "hot_index": "6771965"
        },
        {
            "time": "2025-01-20 02:45:14.081563+08:00",
            "hot_index": "6558205"
        },
        {
            "time": "2025-01-20 03:09:06.022243+08:00",
            "hot_index": "6006690"
        },
        {
            "time": "2025-01-20 03:23:39.746335+08:00",
            "hot_index": "6010644"
        },
        {
            "time": "2025-01-20 03:43:35.673651+08:00",
            "hot_index": "6702004"
        },
        {
            "time": "2025-01-20 04:11:58.732404+08:00",
            "hot_index": "6266607"
        },
        {
            "time": "2025-01-20 04:27:56.486948+08:00",
            "hot_index": "5560980"
        },
        {
            "time": "2025-01-20 04:43:55.614944+08:00",
            "hot_index": "5745097"
        }
    ],
    "滑雪比赛男子获奖金女子拿毛巾": [
        {
            "time": "2025-01-20 00:43:35.569021+08:00",
            "hot_index": "3100000"
        }
    ],
    "第一批回家过年的人已被催婚": [
        {
            "time": "2025-01-20 01:10:01.473454+08:00",
            "hot_index": "6743060"
        }
    ],
    "女孩抽中半扇猪 妈妈笑得合不拢嘴": [
        {
            "time": "2025-01-20 01:10:01.473454+08:00",
            "hot_index": "6485984"
        },
        {
            "time": "2025-01-20 02:14:41.430893+08:00",
            "hot_index": "4664204"
        }
    ],
    "美官员：计划下周一重新上线TikTok": [
        {
            "time": "2025-01-20 01:10:01.473454+08:00",
            "hot_index": "6391251"
        },
        {
            "time": "2025-01-20 01:28:30.912134+08:00",
            "hot_index": "6356208"
        },
        {
            "time": "2025-01-20 01:43:50.192560+08:00",
            "hot_index": "6020514"
        },
        {
            "time": "2025-01-20 02:14:41.430893+08:00",
            "hot_index": "6616490"
        },
        {
            "time": "2025-01-20 02:33:24.127994+08:00",
            "hot_index": "5582241"
        },
        {
            "time": "2025-01-20 02:45:14.081563+08:00",
            "hot_index": "5997290"
        },
        {
            "time": "2025-01-20 03:09:06.022243+08:00",
            "hot_index": "5707561"
        },
        {
            "time": "2025-01-20 03:23:39.746335+08:00",
            "hot_index": "6596282"
        },
        {
            "time": "2025-01-20 03:43:35.673651+08:00",
            "hot_index": "6214577"
        },
        {
            "time": "2025-01-20 04:11:58.732404+08:00",
            "hot_index": "5030805"
        },
        {
            "time": "2025-01-20 04:27:56.486948+08:00",
            "hot_index": "4317267"
        },
        {
            "time": "2025-01-20 04:43:55.614944+08:00",
            "hot_index": "6037121"
        }
    ],
    "冰雕师爆火 日薪可达3500元": [
        {
            "time": "2025-01-20 01:10:01.473454+08:00",
            "hot_index": "6234469"
        }
    ],
    "农民父亲在儿子婚礼现场幽默致辞": [
        {
            "time": "2025-01-20 01:10:01.473454+08:00",
            "hot_index": "6158026"
        },
        {
            "time": "2025-01-20 04:43:55.614944+08:00",
            "hot_index": "3167139"
        }
    ],
    "上海市民通宵排队抢福袋": [
        {
            "time": "2025-01-20 01:10:01.473454+08:00",
            "hot_index": "5139362"
        },
        {
            "time": "2025-01-20 01:43:50.192560+08:00",
            "hot_index": "4595385"
        },
        {
            "time": "2025-01-20 02:14:41.430893+08:00",
            "hot_index": "4972617"
        },
        {
            "time": "2025-01-20 02:45:14.081563+08:00",
            "hot_index": "4667336"
        },
        {
            "time": "2025-01-20 03:09:06.022243+08:00",
            "hot_index": "3100000"
        },
        {
            "time": "2025-01-20 04:27:56.486948+08:00",
            "hot_index": "5780438"
        }
    ],
    "徐梦桃世界杯夺冠": [
        {
            "time": "2025-01-20 01:10:01.473454+08:00",
            "hot_index": "4748967"
        }
    ],
    "杨子称离婚后负责孩子所有费用": [
        {
            "time": "2025-01-20 01:10:01.473454+08:00",
            "hot_index": "3920588"
        },
        {
            "time": "2025-01-20 04:11:58.732404+08:00",
            "hot_index": "3540039"
        },
        {
            "time": "2025-01-20 04:43:55.614944+08:00",
            "hot_index": "4168253"
        }
    ],
    "周受资代表TikTok感谢美国用户": [
        {
            "time": "2025-01-20 01:10:01.473454+08:00",
            "hot_index": "3279986"
        },
        {
            "time": "2025-01-20 02:14:41.430893+08:00",
            "hot_index": "4879841"
        },
        {
            "time": "2025-01-20 03:23:39.746335+08:00",
            "hot_index": "5016316"
        }
    ],
    "主人说想要扫把狗狗转头就去拿": [
        {
            "time": "2025-01-20 01:28:30.912134+08:00",
            "hot_index": "6451898"
        },
        {
            "time": "2025-01-20 02:45:14.081563+08:00",
            "hot_index": "3915371"
        }
    ],
    "尹锡悦回应其支持者闯入法院进行破坏": [
        {
            "time": "2025-01-20 01:28:30.912134+08:00",
            "hot_index": "5511410"
        }
    ],
    "黄仁勋现身英伟达北京年会": [
        {
            "time": "2025-01-20 01:28:30.912134+08:00",
            "hot_index": "4418145"
        },
        {
            "time": "2025-01-20 02:33:24.127994+08:00",
            "hot_index": "3123586"
        },
        {
            "time": "2025-01-20 03:43:35.673651+08:00",
            "hot_index": "5491452"
        }
    ],
    "老夫妻在地窖蒸三千斤糯米酿酒中毒": [
        {
            "time": "2025-01-20 01:28:30.912134+08:00",
            "hot_index": "3398513"
        },
        {
            "time": "2025-01-20 02:45:14.081563+08:00",
            "hot_index": "6639641"
        }
    ],
    "孙佳旭世界杯夺冠": [
        {
            "time": "2025-01-20 01:43:50.192560+08:00",
            "hot_index": "5645370"
        },
        {
            "time": "2025-01-20 04:11:58.732404+08:00",
            "hot_index": "3783009"
        }
    ],
    "以色列国家安全部长辞职": [
        {
            "time": "2025-01-20 01:43:50.192560+08:00",
            "hot_index": "4446331"
        },
        {
            "time": "2025-01-20 04:11:58.732404+08:00",
            "hot_index": "4167149"
        }
    ],
    "节前寒潮强势来袭": [
        {
            "time": "2025-01-20 01:43:50.192560+08:00",
            "hot_index": "4172091"
        }
    ],
    "王鹤棣：工作中我不敷衍任何人": [
        {
            "time": "2025-01-20 02:14:41.430893+08:00",
            "hot_index": "6744204"
        }
    ],
    "泽连斯基签署法令制裁多人": [
        {
            "time": "2025-01-20 02:33:24.127994+08:00",
            "hot_index": "6282268"
        },
        {
            "time": "2025-01-20 03:43:35.673651+08:00",
            "hot_index": "6697438"
        }
    ],
    "李现笑得好像那只张嘴的鞋": [
        {
            "time": "2025-01-20 02:33:24.127994+08:00",
            "hot_index": "3100000"
        },
        {
            "time": "2025-01-20 02:45:14.081563+08:00",
            "hot_index": "4890700"
        },
        {
            "time": "2025-01-20 03:09:06.022243+08:00",
            "hot_index": "6772409"
        },
        {
            "time": "2025-01-20 03:23:39.746335+08:00",
            "hot_index": "3100000"
        },
        {
            "time": "2025-01-20 03:43:35.673651+08:00",
            "hot_index": "4103656"
        },
        {
            "time": "2025-01-20 04:11:58.732404+08:00",
            "hot_index": "6329018"
        },
        {
            "time": "2025-01-20 04:27:56.486948+08:00",
            "hot_index": "6184873"
        },
        {
            "time": "2025-01-20 04:43:55.614944+08:00",
            "hot_index": "4306100"
        }
    ],
    "90后新闻联播主播王音棋主持春晚": [
        {
            "time": "2025-01-20 02:45:14.081563+08:00",
            "hot_index": "5566367"
        },
        {
            "time": "2025-01-20 03:09:06.022243+08:00",
            "hot_index": "6638432"
        },
        {
            "time": "2025-01-20 03:23:39.746335+08:00",
            "hot_index": "6623746"
        },
        {
            "time": "2025-01-20 03:43:35.673651+08:00",
            "hot_index": "5153716"
        },
        {
            "time": "2025-01-20 04:11:58.732404+08:00",
            "hot_index": "4753438"
        },
        {
            "time": "2025-01-20 04:27:56.486948+08:00",
            "hot_index": "5885201"
        },
        {
            "time": "2025-01-20 04:43:55.614944+08:00",
            "hot_index": "6325078"
        }
    ],
    "内马尔谈巴黎生涯失败原因": [
        {
            "time": "2025-01-20 03:09:06.022243+08:00",
            "hot_index": "4738235"
        }
    ],
    "妈妈每天拍女儿匆忙上班的背影": [
        {
            "time": "2025-01-20 03:23:39.746335+08:00",
            "hot_index": "3669073"
        }
    ],
    "游本昌首次与孙女同台": [
        {
            "time": "2025-01-20 03:23:39.746335+08:00",
            "hot_index": "3236769"
        },
        {
            "time": "2025-01-20 03:43:35.673651+08:00",
            "hot_index": "5309743"
        },
        {
            "time": "2025-01-20 04:11:58.732404+08:00",
            "hot_index": "6150735"
        },
        {
            "time": "2025-01-20 04:27:56.486948+08:00",
            "hot_index": "6359543"
        },
        {
            "time": "2025-01-20 04:43:55.614944+08:00",
            "hot_index": "6417268"
        }
    ],
    "顺丰等多家快递公司表示春节不停运": [
        {
            "time": "2025-01-20 04:27:56.486948+08:00",
            "hot_index": "4192218"
        }
    ],
    "漂白 王千源好恐怖的表白": [
        {
            "time": "2025-01-20 04:43:55.614944+08:00",
            "hot_index": "3713069"
        }
    ]
}