{
    "以中国新发展为世界提供新机遇": [
        {
            "time": "2023-11-06 00:10:48.020815+08:00",
            "hot_index": "4983049"
        },
        {
            "time": "2023-11-06 00:30:52.007571+08:00",
            "hot_index": "4952986"
        },
        {
            "time": "2023-11-06 00:43:27.099929+08:00",
            "hot_index": "4946739"
        },
        {
            "time": "2023-11-06 01:07:59.594880+08:00",
            "hot_index": "4995266"
        },
        {
            "time": "2023-11-06 01:25:40.996615+08:00",
            "hot_index": "4940612"
        },
        {
            "time": "2023-11-06 01:43:28.149848+08:00",
            "hot_index": "4951065"
        },
        {
            "time": "2023-11-06 02:10:46.582185+08:00",
            "hot_index": "4986393"
        },
        {
            "time": "2023-11-06 02:27:29.032422+08:00",
            "hot_index": "4962321"
        }
    ],
    "财政部部长晒国家“账本”": [
        {
            "time": "2023-11-06 00:10:48.020815+08:00",
            "hot_index": "4979265"
        },
        {
            "time": "2023-11-06 00:30:52.007571+08:00",
            "hot_index": "4976492"
        },
        {
            "time": "2023-11-06 00:43:27.099929+08:00",
            "hot_index": "4987594"
        },
        {
            "time": "2023-11-06 01:07:59.594880+08:00",
            "hot_index": "4944315"
        },
        {
            "time": "2023-11-06 01:25:40.996615+08:00",
            "hot_index": "4984120"
        },
        {
            "time": "2023-11-06 01:43:28.149848+08:00",
            "hot_index": "4975236"
        },
        {
            "time": "2023-11-06 02:10:46.582185+08:00",
            "hot_index": "4912804"
        },
        {
            "time": "2023-11-06 02:27:29.032422+08:00",
            "hot_index": "4965250"
        }
    ],
    "男子称因脸太方应聘多家工厂被拒": [
        {
            "time": "2023-11-06 00:10:48.020815+08:00",
            "hot_index": "4872659"
        },
        {
            "time": "2023-11-06 00:30:52.007571+08:00",
            "hot_index": "4807006"
        },
        {
            "time": "2023-11-06 00:43:27.099929+08:00",
            "hot_index": "4819667"
        },
        {
            "time": "2023-11-06 01:07:59.594880+08:00",
            "hot_index": "4808398"
        },
        {
            "time": "2023-11-06 01:25:40.996615+08:00",
            "hot_index": "4801065"
        },
        {
            "time": "2023-11-06 01:43:28.149848+08:00",
            "hot_index": "4897391"
        },
        {
            "time": "2023-11-06 02:10:46.582185+08:00",
            "hot_index": "4883511"
        },
        {
            "time": "2023-11-06 02:27:29.032422+08:00",
            "hot_index": "4847083"
        }
    ],
    "共“进”向未来 “博”出新精彩": [
        {
            "time": "2023-11-06 00:10:48.020815+08:00",
            "hot_index": "4717445"
        },
        {
            "time": "2023-11-06 00:30:52.007571+08:00",
            "hot_index": "4776470"
        },
        {
            "time": "2023-11-06 00:43:27.099929+08:00",
            "hot_index": "4789279"
        },
        {
            "time": "2023-11-06 01:07:59.594880+08:00",
            "hot_index": "4799740"
        },
        {
            "time": "2023-11-06 01:25:40.996615+08:00",
            "hot_index": "4742635"
        },
        {
            "time": "2023-11-06 01:43:28.149848+08:00",
            "hot_index": "4745283"
        },
        {
            "time": "2023-11-06 02:10:46.582185+08:00",
            "hot_index": "4726643"
        },
        {
            "time": "2023-11-06 02:27:29.032422+08:00",
            "hot_index": "4772001"
        }
    ],
    "县民政局局长违规操办婚事被免职": [
        {
            "time": "2023-11-06 00:10:48.020815+08:00",
            "hot_index": "4647965"
        },
        {
            "time": "2023-11-06 00:30:52.007571+08:00",
            "hot_index": "4698912"
        },
        {
            "time": "2023-11-06 00:43:27.099929+08:00",
            "hot_index": "4614239"
        },
        {
            "time": "2023-11-06 01:07:59.594880+08:00",
            "hot_index": "4695144"
        },
        {
            "time": "2023-11-06 01:25:40.996615+08:00",
            "hot_index": "4681213"
        },
        {
            "time": "2023-11-06 01:43:28.149848+08:00",
            "hot_index": "4647880"
        },
        {
            "time": "2023-11-06 02:10:46.582185+08:00",
            "hot_index": "4686679"
        },
        {
            "time": "2023-11-06 02:27:29.032422+08:00",
            "hot_index": "4628218"
        }
    ],
    "奥巴马谈巴以冲突": [
        {
            "time": "2023-11-06 00:10:48.020815+08:00",
            "hot_index": "4565046"
        },
        {
            "time": "2023-11-06 00:30:52.007571+08:00",
            "hot_index": "4455354"
        },
        {
            "time": "2023-11-06 00:43:27.099929+08:00",
            "hot_index": "4490641"
        },
        {
            "time": "2023-11-06 01:07:59.594880+08:00",
            "hot_index": "3908866"
        },
        {
            "time": "2023-11-06 01:25:40.996615+08:00",
            "hot_index": "2788197"
        },
        {
            "time": "2023-11-06 01:43:28.149848+08:00",
            "hot_index": "3179202"
        },
        {
            "time": "2023-11-06 02:10:46.582185+08:00",
            "hot_index": "4455405"
        },
        {
            "time": "2023-11-06 02:27:29.032422+08:00",
            "hot_index": "3903468"
        }
    ],
    "加沙每10分钟就有一儿童死亡": [
        {
            "time": "2023-11-06 00:10:48.020815+08:00",
            "hot_index": "4405000"
        },
        {
            "time": "2023-11-06 01:25:40.996615+08:00",
            "hot_index": "4571975"
        }
    ],
    "女孩身上6个伤疤同寻人启事一致": [
        {
            "time": "2023-11-06 00:10:48.020815+08:00",
            "hot_index": "4359443"
        },
        {
            "time": "2023-11-06 00:30:52.007571+08:00",
            "hot_index": "2799258"
        },
        {
            "time": "2023-11-06 00:43:27.099929+08:00",
            "hot_index": "3621900"
        },
        {
            "time": "2023-11-06 01:07:59.594880+08:00",
            "hot_index": "3497599"
        },
        {
            "time": "2023-11-06 01:25:40.996615+08:00",
            "hot_index": "3829421"
        },
        {
            "time": "2023-11-06 01:43:28.149848+08:00",
            "hot_index": "3655151"
        },
        {
            "time": "2023-11-06 02:10:46.582185+08:00",
            "hot_index": "3144811"
        },
        {
            "time": "2023-11-06 02:27:29.032422+08:00",
            "hot_index": "3857219"
        }
    ],
    "网传低价代缴采暖费？别信！": [
        {
            "time": "2023-11-06 00:10:48.020815+08:00",
            "hot_index": "4277809"
        }
    ],
    "尼泊尔强震致房屋大面积倒塌": [
        {
            "time": "2023-11-06 00:10:48.020815+08:00",
            "hot_index": "4139309"
        }
    ],
    "刘昊然回应一部手机用五六年": [
        {
            "time": "2023-11-06 00:10:48.020815+08:00",
            "hot_index": "4060601"
        },
        {
            "time": "2023-11-06 00:30:52.007571+08:00",
            "hot_index": "4095223"
        },
        {
            "time": "2023-11-06 00:43:27.099929+08:00",
            "hot_index": "4051404"
        },
        {
            "time": "2023-11-06 01:07:59.594880+08:00",
            "hot_index": "4069698"
        },
        {
            "time": "2023-11-06 01:25:40.996615+08:00",
            "hot_index": "4018613"
        },
        {
            "time": "2023-11-06 01:43:28.149848+08:00",
            "hot_index": "3992639"
        },
        {
            "time": "2023-11-06 02:10:46.582185+08:00",
            "hot_index": "4088290"
        },
        {
            "time": "2023-11-06 02:27:29.032422+08:00",
            "hot_index": "2818848"
        }
    ],
    "女子曝足疗店按摩被男技师猥亵": [
        {
            "time": "2023-11-06 00:10:48.020815+08:00",
            "hot_index": "3930265"
        },
        {
            "time": "2023-11-06 00:30:52.007571+08:00",
            "hot_index": "3800678"
        },
        {
            "time": "2023-11-06 00:43:27.099929+08:00",
            "hot_index": "3786739"
        },
        {
            "time": "2023-11-06 01:07:59.594880+08:00",
            "hot_index": "3764785"
        },
        {
            "time": "2023-11-06 01:25:40.996615+08:00",
            "hot_index": "3922375"
        },
        {
            "time": "2023-11-06 01:43:28.149848+08:00",
            "hot_index": "3894719"
        },
        {
            "time": "2023-11-06 02:10:46.582185+08:00",
            "hot_index": "3433995"
        },
        {
            "time": "2023-11-06 02:27:29.032422+08:00",
            "hot_index": "3423055"
        }
    ],
    "巴菲特巨亏近1000亿": [
        {
            "time": "2023-11-06 00:10:48.020815+08:00",
            "hot_index": "3890903"
        },
        {
            "time": "2023-11-06 00:30:52.007571+08:00",
            "hot_index": "3417171"
        },
        {
            "time": "2023-11-06 00:43:27.099929+08:00",
            "hot_index": "2659937"
        },
        {
            "time": "2023-11-06 01:07:59.594880+08:00",
            "hot_index": "2307276"
        },
        {
            "time": "2023-11-06 01:25:40.996615+08:00",
            "hot_index": "2827559"
        },
        {
            "time": "2023-11-06 01:43:28.149848+08:00",
            "hot_index": "2700974"
        },
        {
            "time": "2023-11-06 02:10:46.582185+08:00",
            "hot_index": "2452461"
        },
        {
            "time": "2023-11-06 02:27:29.032422+08:00",
            "hot_index": "2581472"
        }
    ],
    "浙江一校长办公室变肠胃外科": [
        {
            "time": "2023-11-06 00:10:48.020815+08:00",
            "hot_index": "3760635"
        },
        {
            "time": "2023-11-06 00:30:52.007571+08:00",
            "hot_index": "3332482"
        },
        {
            "time": "2023-11-06 00:43:27.099929+08:00",
            "hot_index": "3239836"
        },
        {
            "time": "2023-11-06 01:07:59.594880+08:00",
            "hot_index": "3306460"
        },
        {
            "time": "2023-11-06 01:25:40.996615+08:00",
            "hot_index": "3221097"
        }
    ],
    "广东揭阳多车碰撞致1死9伤": [
        {
            "time": "2023-11-06 00:10:48.020815+08:00",
            "hot_index": "3680618"
        }
    ],
    "中国战地女记者陈慧慧成功撤离": [
        {
            "time": "2023-11-06 00:10:48.020815+08:00",
            "hot_index": "3582935"
        },
        {
            "time": "2023-11-06 00:30:52.007571+08:00",
            "hot_index": "2831391"
        },
        {
            "time": "2023-11-06 00:43:27.099929+08:00",
            "hot_index": "3114885"
        },
        {
            "time": "2023-11-06 01:07:59.594880+08:00",
            "hot_index": "2591289"
        },
        {
            "time": "2023-11-06 01:25:40.996615+08:00",
            "hot_index": "3155579"
        },
        {
            "time": "2023-11-06 01:43:28.149848+08:00",
            "hot_index": "2490534"
        },
        {
            "time": "2023-11-06 02:10:46.582185+08:00",
            "hot_index": "2285039"
        },
        {
            "time": "2023-11-06 02:27:29.032422+08:00",
            "hot_index": "2379010"
        }
    ],
    "女生晒合影被盗图造谣:评论不堪入目": [
        {
            "time": "2023-11-06 00:10:48.020815+08:00",
            "hot_index": "3422379"
        }
    ],
    "月薪五千借钱给儿子买万元电脑": [
        {
            "time": "2023-11-06 00:10:48.020815+08:00",
            "hot_index": "3398583"
        },
        {
            "time": "2023-11-06 00:30:52.007571+08:00",
            "hot_index": "3706923"
        },
        {
            "time": "2023-11-06 00:43:27.099929+08:00",
            "hot_index": "3850779"
        },
        {
            "time": "2023-11-06 01:07:59.594880+08:00",
            "hot_index": "3048369"
        },
        {
            "time": "2023-11-06 01:25:40.996615+08:00",
            "hot_index": "2620620"
        },
        {
            "time": "2023-11-06 01:43:28.149848+08:00",
            "hot_index": "4004088"
        },
        {
            "time": "2023-11-06 02:10:46.582185+08:00",
            "hot_index": "2863195"
        },
        {
            "time": "2023-11-06 02:27:29.032422+08:00",
            "hot_index": "3102177"
        }
    ],
    "受暴雪影响 东北地区多趟列车停运": [
        {
            "time": "2023-11-06 00:10:48.020815+08:00",
            "hot_index": "3242038"
        }
    ],
    "媒体：挤占助学金的伪贫困生有多少": [
        {
            "time": "2023-11-06 00:10:48.020815+08:00",
            "hot_index": "3171968"
        },
        {
            "time": "2023-11-06 01:25:40.996615+08:00",
            "hot_index": "4444119"
        }
    ],
    "福原爱或面临2年以上有期徒刑": [
        {
            "time": "2023-11-06 00:10:48.020815+08:00",
            "hot_index": "3032643"
        },
        {
            "time": "2023-11-06 00:30:52.007571+08:00",
            "hot_index": "3645304"
        },
        {
            "time": "2023-11-06 00:43:27.099929+08:00",
            "hot_index": "3552014"
        },
        {
            "time": "2023-11-06 01:07:59.594880+08:00",
            "hot_index": "3596395"
        },
        {
            "time": "2023-11-06 01:25:40.996615+08:00",
            "hot_index": "3080554"
        },
        {
            "time": "2023-11-06 01:43:28.149848+08:00",
            "hot_index": "3331279"
        },
        {
            "time": "2023-11-06 02:10:46.582185+08:00",
            "hot_index": "3607828"
        },
        {
            "time": "2023-11-06 02:27:29.032422+08:00",
            "hot_index": "3222572"
        }
    ],
    "南京暴雨 萧敬腾从不失手": [
        {
            "time": "2023-11-06 00:10:48.020815+08:00",
            "hot_index": "2916497"
        },
        {
            "time": "2023-11-06 00:30:52.007571+08:00",
            "hot_index": "3030628"
        },
        {
            "time": "2023-11-06 00:43:27.099929+08:00",
            "hot_index": "2766386"
        },
        {
            "time": "2023-11-06 01:07:59.594880+08:00",
            "hot_index": "2710629"
        }
    ],
    "澳总理：7年来首访华是耐心的成果": [
        {
            "time": "2023-11-06 00:10:48.020815+08:00",
            "hot_index": "2897182"
        },
        {
            "time": "2023-11-06 01:25:40.996615+08:00",
            "hot_index": "3647149"
        }
    ],
    "台黑帮头目向好友炫枪时将自己打死": [
        {
            "time": "2023-11-06 00:10:48.020815+08:00",
            "hot_index": "2734037"
        },
        {
            "time": "2023-11-06 00:30:52.007571+08:00",
            "hot_index": "2921191"
        },
        {
            "time": "2023-11-06 00:43:27.099929+08:00",
            "hot_index": "2864304"
        },
        {
            "time": "2023-11-06 01:07:59.594880+08:00",
            "hot_index": "2989396"
        },
        {
            "time": "2023-11-06 01:25:40.996615+08:00",
            "hot_index": "2963953"
        },
        {
            "time": "2023-11-06 01:43:28.149848+08:00",
            "hot_index": "2847608"
        },
        {
            "time": "2023-11-06 02:10:46.582185+08:00",
            "hot_index": "2963097"
        },
        {
            "time": "2023-11-06 02:27:29.032422+08:00",
            "hot_index": "2722059"
        }
    ],
    "李显龙哽咽了": [
        {
            "time": "2023-11-06 00:10:48.020815+08:00",
            "hot_index": "2626287"
        },
        {
            "time": "2023-11-06 00:30:52.007571+08:00",
            "hot_index": "3276028"
        },
        {
            "time": "2023-11-06 00:43:27.099929+08:00",
            "hot_index": "4121979"
        },
        {
            "time": "2023-11-06 01:07:59.594880+08:00",
            "hot_index": "3883371"
        },
        {
            "time": "2023-11-06 01:25:40.996615+08:00",
            "hot_index": "3324030"
        },
        {
            "time": "2023-11-06 01:43:28.149848+08:00",
            "hot_index": "2501524"
        },
        {
            "time": "2023-11-06 02:10:46.582185+08:00",
            "hot_index": "3891098"
        },
        {
            "time": "2023-11-06 02:27:29.032422+08:00",
            "hot_index": "4121169"
        }
    ],
    "茅台提价之后 原箱价格一天三涨": [
        {
            "time": "2023-11-06 00:10:48.020815+08:00",
            "hot_index": "2516480"
        }
    ],
    "骗子准确说出信息大学生被骗350万": [
        {
            "time": "2023-11-06 00:10:48.020815+08:00",
            "hot_index": "2419430"
        },
        {
            "time": "2023-11-06 00:30:52.007571+08:00",
            "hot_index": "2573195"
        },
        {
            "time": "2023-11-06 00:43:27.099929+08:00",
            "hot_index": "3976640"
        },
        {
            "time": "2023-11-06 01:07:59.594880+08:00",
            "hot_index": "4181640"
        },
        {
            "time": "2023-11-06 01:25:40.996615+08:00",
            "hot_index": "2464717"
        },
        {
            "time": "2023-11-06 01:43:28.149848+08:00",
            "hot_index": "2071596"
        },
        {
            "time": "2023-11-06 02:10:46.582185+08:00",
            "hot_index": "4557848"
        },
        {
            "time": "2023-11-06 02:27:29.032422+08:00",
            "hot_index": "4021795"
        }
    ],
    "八旬老人拄拐拦婚车要钱": [
        {
            "time": "2023-11-06 00:10:48.020815+08:00",
            "hot_index": "2361415"
        }
    ],
    "俄方驳斥普京有众多“替身”猜测": [
        {
            "time": "2023-11-06 00:10:48.020815+08:00",
            "hot_index": "2210372"
        },
        {
            "time": "2023-11-06 01:25:40.996615+08:00",
            "hot_index": "2273492"
        }
    ],
    "疑因打车价格与司机争执 女子跳车": [
        {
            "time": "2023-11-06 00:10:48.020815+08:00",
            "hot_index": "2161136"
        },
        {
            "time": "2023-11-06 01:25:40.996615+08:00",
            "hot_index": "3528111"
        }
    ],
    "黑龙江一市因暴雪停课停工停产": [
        {
            "time": "2023-11-06 00:10:48.020815+08:00",
            "hot_index": "2004305"
        },
        {
            "time": "2023-11-06 00:30:52.007571+08:00",
            "hot_index": "2060847"
        },
        {
            "time": "2023-11-06 00:43:27.099929+08:00",
            "hot_index": "3492354"
        },
        {
            "time": "2023-11-06 01:07:59.594880+08:00",
            "hot_index": "3249585"
        },
        {
            "time": "2023-11-06 01:25:40.996615+08:00",
            "hot_index": "4348140"
        },
        {
            "time": "2023-11-06 01:43:28.149848+08:00",
            "hot_index": "3485128"
        },
        {
            "time": "2023-11-06 02:10:46.582185+08:00",
            "hot_index": "3024981"
        },
        {
            "time": "2023-11-06 02:27:29.032422+08:00",
            "hot_index": "4351183"
        }
    ],
    "接连三震正常吗？广东地震台回应": [
        {
            "time": "2023-11-06 00:30:52.007571+08:00",
            "hot_index": "4522683"
        },
        {
            "time": "2023-11-06 01:43:28.149848+08:00",
            "hot_index": "3280753"
        }
    ],
    "货车轮胎打气时爆炸 3人被弹飞": [
        {
            "time": "2023-11-06 00:30:52.007571+08:00",
            "hot_index": "4386384"
        }
    ],
    "网传外卖员年龄上限45岁系谣言": [
        {
            "time": "2023-11-06 00:30:52.007571+08:00",
            "hot_index": "4273951"
        },
        {
            "time": "2023-11-06 00:43:27.099929+08:00",
            "hot_index": "4204562"
        },
        {
            "time": "2023-11-06 01:07:59.594880+08:00",
            "hot_index": "4255885"
        },
        {
            "time": "2023-11-06 01:25:40.996615+08:00",
            "hot_index": "4297466"
        },
        {
            "time": "2023-11-06 01:43:28.149848+08:00",
            "hot_index": "4258588"
        },
        {
            "time": "2023-11-06 02:10:46.582185+08:00",
            "hot_index": "4276507"
        },
        {
            "time": "2023-11-06 02:27:29.032422+08:00",
            "hot_index": "4223668"
        }
    ],
    "布林肯会见巴勒斯坦总统阿巴斯": [
        {
            "time": "2023-11-06 00:30:52.007571+08:00",
            "hot_index": "4170039"
        },
        {
            "time": "2023-11-06 01:43:28.149848+08:00",
            "hot_index": "4370352"
        }
    ],
    "俄新型战略核潜艇试射弹道导弹": [
        {
            "time": "2023-11-06 00:30:52.007571+08:00",
            "hot_index": "3917816"
        }
    ],
    "曝美欧乌已商讨与俄“和谈条件”": [
        {
            "time": "2023-11-06 00:30:52.007571+08:00",
            "hot_index": "3516442"
        },
        {
            "time": "2023-11-06 01:43:28.149848+08:00",
            "hot_index": "4524475"
        }
    ],
    "韩星李善均承认吸毒": [
        {
            "time": "2023-11-06 00:30:52.007571+08:00",
            "hot_index": "3133231"
        },
        {
            "time": "2023-11-06 01:43:28.149848+08:00",
            "hot_index": "3756532"
        }
    ],
    "男子帮业主疏通管道掏出娃娃鱼": [
        {
            "time": "2023-11-06 00:30:52.007571+08:00",
            "hot_index": "2610367"
        },
        {
            "time": "2023-11-06 01:25:40.996615+08:00",
            "hot_index": "2011157"
        }
    ],
    "顾客套中3只大鹅 老板耍赖装晕倒": [
        {
            "time": "2023-11-06 00:30:52.007571+08:00",
            "hot_index": "2487713"
        },
        {
            "time": "2023-11-06 00:43:27.099929+08:00",
            "hot_index": "2528485"
        },
        {
            "time": "2023-11-06 01:07:59.594880+08:00",
            "hot_index": "2038943"
        }
    ],
    "保时捷：市场规模尚无法支撑国产": [
        {
            "time": "2023-11-06 00:30:52.007571+08:00",
            "hot_index": "2380537"
        },
        {
            "time": "2023-11-06 00:43:27.099929+08:00",
            "hot_index": "2160441"
        },
        {
            "time": "2023-11-06 01:43:28.149848+08:00",
            "hot_index": "2163923"
        },
        {
            "time": "2023-11-06 02:10:46.582185+08:00",
            "hot_index": "2773296"
        },
        {
            "time": "2023-11-06 02:27:29.032422+08:00",
            "hot_index": "2209806"
        }
    ],
    "网红一笑倾城停更76天后复更": [
        {
            "time": "2023-11-06 00:30:52.007571+08:00",
            "hot_index": "2273903"
        },
        {
            "time": "2023-11-06 00:43:27.099929+08:00",
            "hot_index": "2454902"
        },
        {
            "time": "2023-11-06 02:10:46.582185+08:00",
            "hot_index": "2101396"
        },
        {
            "time": "2023-11-06 02:27:29.032422+08:00",
            "hot_index": "2642494"
        }
    ],
    "毛毛姐称直播间手机被调包成模型机": [
        {
            "time": "2023-11-06 00:30:52.007571+08:00",
            "hot_index": "2131934"
        }
    ],
    "黑龙江发布暴雪红色预警": [
        {
            "time": "2023-11-06 00:43:27.099929+08:00",
            "hot_index": "4538464"
        }
    ],
    "以方誓言消灭哈马斯加沙领导人": [
        {
            "time": "2023-11-06 00:43:27.099929+08:00",
            "hot_index": "4333079"
        }
    ],
    "酒店回应女子3000元服装被保洁撕碎": [
        {
            "time": "2023-11-06 00:43:27.099929+08:00",
            "hot_index": "3333456"
        }
    ],
    "航班飞行中乘客欲打开舱门被阻止": [
        {
            "time": "2023-11-06 00:43:27.099929+08:00",
            "hot_index": "3020428"
        }
    ],
    "公职人员猥亵女孩仅拘9天？纪委介入": [
        {
            "time": "2023-11-06 00:43:27.099929+08:00",
            "hot_index": "2951440"
        },
        {
            "time": "2023-11-06 01:43:28.149848+08:00",
            "hot_index": "2916973"
        },
        {
            "time": "2023-11-06 02:27:29.032422+08:00",
            "hot_index": "2452387"
        }
    ],
    "手握800亿 美的为什么去香港？": [
        {
            "time": "2023-11-06 00:43:27.099929+08:00",
            "hot_index": "2351384"
        },
        {
            "time": "2023-11-06 01:07:59.594880+08:00",
            "hot_index": "2653004"
        },
        {
            "time": "2023-11-06 01:25:40.996615+08:00",
            "hot_index": "3406464"
        },
        {
            "time": "2023-11-06 01:43:28.149848+08:00",
            "hot_index": "3599220"
        },
        {
            "time": "2023-11-06 02:10:46.582185+08:00",
            "hot_index": "3793068"
        },
        {
            "time": "2023-11-06 02:27:29.032422+08:00",
            "hot_index": "3503315"
        }
    ],
    "3元以下的饮料要消失了？": [
        {
            "time": "2023-11-06 00:43:27.099929+08:00",
            "hot_index": "2276215"
        },
        {
            "time": "2023-11-06 01:25:40.996615+08:00",
            "hot_index": "2390794"
        },
        {
            "time": "2023-11-06 01:43:28.149848+08:00",
            "hot_index": "3018151"
        },
        {
            "time": "2023-11-06 02:10:46.582185+08:00",
            "hot_index": "2685007"
        },
        {
            "time": "2023-11-06 02:27:29.032422+08:00",
            "hot_index": "3078862"
        }
    ],
    "央视关注电子门锁故障频发现象": [
        {
            "time": "2023-11-06 00:43:27.099929+08:00",
            "hot_index": "2016497"
        }
    ],
    "东北此次雨雪量或破历史同期极值": [
        {
            "time": "2023-11-06 01:07:59.594880+08:00",
            "hot_index": "4579050"
        },
        {
            "time": "2023-11-06 02:10:46.582185+08:00",
            "hot_index": "4327571"
        }
    ],
    "儿科已出现流感与支原体交叉感染": [
        {
            "time": "2023-11-06 01:07:59.594880+08:00",
            "hot_index": "4444541"
        }
    ],
    "美代表团称访华行大开眼界": [
        {
            "time": "2023-11-06 01:07:59.594880+08:00",
            "hot_index": "4368251"
        },
        {
            "time": "2023-11-06 02:10:46.582185+08:00",
            "hot_index": "3527763"
        }
    ],
    "何小鹏喊话“不知道他急什么”": [
        {
            "time": "2023-11-06 01:07:59.594880+08:00",
            "hot_index": "3634197"
        }
    ],
    "打工人职场头像学": [
        {
            "time": "2023-11-06 01:07:59.594880+08:00",
            "hot_index": "3111579"
        }
    ],
    "如何预防食源性肉毒中毒": [
        {
            "time": "2023-11-06 01:07:59.594880+08:00",
            "hot_index": "2821575"
        }
    ],
    "韩国将暂时禁止股票卖空": [
        {
            "time": "2023-11-06 01:07:59.594880+08:00",
            "hot_index": "2494278"
        }
    ],
    "白宫墙上出现“血手印”": [
        {
            "time": "2023-11-06 01:07:59.594880+08:00",
            "hot_index": "2284128"
        },
        {
            "time": "2023-11-06 02:10:46.582185+08:00",
            "hot_index": "2382546"
        },
        {
            "time": "2023-11-06 02:27:29.032422+08:00",
            "hot_index": "2108383"
        }
    ],
    "村民砍伐自家514株林木被刑拘": [
        {
            "time": "2023-11-06 01:07:59.594880+08:00",
            "hot_index": "2182002"
        },
        {
            "time": "2023-11-06 01:43:28.149848+08:00",
            "hot_index": "2357586"
        },
        {
            "time": "2023-11-06 02:10:46.582185+08:00",
            "hot_index": "3216834"
        },
        {
            "time": "2023-11-06 02:27:29.032422+08:00",
            "hot_index": "3395904"
        }
    ],
    "蜜雪冰城门店经理猥亵女员工被拘": [
        {
            "time": "2023-11-06 01:25:40.996615+08:00",
            "hot_index": "4104187"
        }
    ],
    "菲主播遭入室枪杀 总统下令彻查": [
        {
            "time": "2023-11-06 01:25:40.996615+08:00",
            "hot_index": "3724206"
        }
    ],
    "GALA哭了": [
        {
            "time": "2023-11-06 01:25:40.996615+08:00",
            "hot_index": "2579585"
        },
        {
            "time": "2023-11-06 01:43:28.149848+08:00",
            "hot_index": "2274142"
        },
        {
            "time": "2023-11-06 02:10:46.582185+08:00",
            "hot_index": "3353594"
        },
        {
            "time": "2023-11-06 02:27:29.032422+08:00",
            "hot_index": "3605302"
        }
    ],
    "吉林一医院上空有大量飞鸟盘旋": [
        {
            "time": "2023-11-06 01:25:40.996615+08:00",
            "hot_index": "2172952"
        },
        {
            "time": "2023-11-06 01:43:28.149848+08:00",
            "hot_index": "2682082"
        },
        {
            "time": "2023-11-06 02:10:46.582185+08:00",
            "hot_index": "2568844"
        },
        {
            "time": "2023-11-06 02:27:29.032422+08:00",
            "hot_index": "2997191"
        }
    ],
    "宝妈发现母婴室被人用来吸烟约会": [
        {
            "time": "2023-11-06 01:43:28.149848+08:00",
            "hot_index": "4405303"
        }
    ],
    "干部商人围坐“诈金花”？官方调查": [
        {
            "time": "2023-11-06 01:43:28.149848+08:00",
            "hot_index": "4109799"
        }
    ],
    "四预警齐发 多地气温将猛降16℃": [
        {
            "time": "2023-11-06 02:10:46.582185+08:00",
            "hot_index": "4185042"
        }
    ],
    "大妈为自拍不慎踩空掉进芦苇荡": [
        {
            "time": "2023-11-06 02:10:46.582185+08:00",
            "hot_index": "3992334"
        }
    ],
    "作家周涛突发心梗去世": [
        {
            "time": "2023-11-06 02:10:46.582185+08:00",
            "hot_index": "2014753"
        }
    ],
    "大三女生车祸离世捐出所有器官": [
        {
            "time": "2023-11-06 02:27:29.032422+08:00",
            "hot_index": "4580199"
        }
    ],
    "过山车立柱大幅晃动？广州长隆回应": [
        {
            "time": "2023-11-06 02:27:29.032422+08:00",
            "hot_index": "4421157"
        }
    ],
    "知名运动员因感染支原体肺炎退赛": [
        {
            "time": "2023-11-06 02:27:29.032422+08:00",
            "hot_index": "3724790"
        }
    ],
    "麻辣烫贵到40块都吃不饱": [
        {
            "time": "2023-11-06 02:27:29.032422+08:00",
            "hot_index": "2003897"
        }
    ]
}